{"co":"Denmark","coD":"Denmark","players":[{"n":"William Bloch","h":193,"p":"G","y":2005,"nat":"Danska","c":"BAKKEN BEARS AARHUS","co":"Denmark","coD":"Denmark","s":"left","to":"Bears Academy","tl":"BasketLigaen","isComp":false,"url":"https://basketball.eurobasket.com/player/William-Bloch/663406"},{"n":"Duke Deen","h":173,"p":"PG","y":2001,"nat":"ZDA","c":"BAKKEN BEARS AARHUS","co":"Denmark","coD":"Denmark","s":"left","to":"Denain-Voltaire","tl":"ProB","isComp":false,"url":"https://basketball.eurobasket.com/player/Duke-Deen/526558"},{"n":"Simon Schwartz","h":205,"p":"F","y":2004,"nat":"Danska","c":"BAKKEN BEARS AARHUS","co":"Denmark","coD":"Denmark","s":"left","to":"Gladsaxe","tl":"1st Division","isComp":false,"url":"https://basketball.eurobasket.com/player/Simon-Schwartz/620667"},{"n":"Tymu Chenery","h":198,"p":"G","y":2000,"nat":"ZDA","c":"BAKKEN BEARS AARHUS","co":"Denmark","coD":"Denmark","s":"free","to":null,"tl":null,"isComp":false,"url":"https://basketball.eurobasket.com/player/Tymu-Chenery/564258"},{"n":"Ian DuBose","h":193,"p":"G","y":1999,"nat":"ZDA","c":"BAKKEN BEARS AARHUS","co":"Denmark","coD":"Denmark","s":"free","to":null,"tl":null,"isComp":false,"url":"https://basketball.eurobasket.com/player/Ian-DuBose/447522"},{"n":"Kai Edwards","h":206,"p":"C/F","y":1997,"nat":"Nizozemska","c":"BAKKEN BEARS AARHUS","co":"Denmark","coD":"Denmark","s":"free","to":null,"tl":null,"isComp":false,"url":"https://basketball.eurobasket.com/player/Kai-Edwards/400297"},{"n":"Oscar Jorgensen","h":187,"p":"G","y":1998,"nat":null,"c":"BAKKEN BEARS AARHUS","co":"Denmark","coD":"Denmark","s":"free","to":null,"tl":null,"isComp":false,"url":null},{"n":"Anton Katholm","h":200,"p":"F","y":2007,"nat":null,"c":"BAKKEN BEARS AARHUS","co":"Denmark","coD":"Denmark","s":"free","to":null,"tl":null,"isComp":false,"url":null},{"n":"Magnus Mollgaard","h":200,"p":"G","y":2000,"nat":null,"c":"BAKKEN BEARS AARHUS","co":"Denmark","coD":"Denmark","s":"free","to":null,"tl":null,"isComp":false,"url":null},{"n":"Shaquille Rombley","h":203,"p":"C","y":1996,"nat":"Nizozemska","c":"BAKKEN BEARS AARHUS","co":"Denmark","coD":"Denmark","s":"free","to":null,"tl":null,"isComp":false,"url":"https://basketball.eurobasket.com/player/Shaquille-Rombley/429619"},{"n":"Sam Sherry","h":208,"p":"F","y":2002,"nat":"ZDA","c":"BAKKEN BEARS AARHUS","co":"Denmark","coD":"Denmark","s":"free","to":null,"tl":null,"isComp":false,"url":"https://basketball.eurobasket.com/player/Sam-Sherry/598178"},{"n":"Filip Ates","h":186,"p":"G","y":2004,"nat":null,"c":"BAKKEN BEARS AARHUS","co":"Denmark","coD":"Denmark","s":"free","to":null,"tl":null,"isComp":false,"url":null},{"n":"Sylvester Pedersen","h":201,"p":"F","y":1998,"nat":null,"c":"BAKKEN BEARS AARHUS","co":"Denmark","coD":"Denmark","s":"free","to":null,"tl":null,"isComp":false,"url":null},{"n":"Markus Vinther","h":195,"p":"G","y":2002,"nat":null,"c":"BAKKEN BEARS AARHUS","co":"Denmark","coD":"Denmark","s":"free","to":null,"tl":null,"isComp":false,"url":null},{"n":"Darko Jukic","h":199,"p":"G","y":1990,"nat":null,"c":"BAKKEN BEARS AARHUS","co":"Denmark","coD":"Denmark","s":"free","to":null,"tl":null,"isComp":false,"url":null},{"n":"Andrew Ramirez","h":181,"p":"PG","y":1997,"nat":"Španija","c":"BASKETBALL CLUB COPENHAGEN","co":"Denmark","coD":"Denmark","s":null,"to":null,"tl":null,"isComp":false,"url":"https://basketball.eurobasket.com/player/Andrew-Ramirez/284462"},{"n":"Emil Grosse","h":208,"p":"F","y":2003,"nat":"Norveška","c":"BASKETBALL CLUB COPENHAGEN","co":"Denmark","coD":"Denmark","s":"free","to":null,"tl":null,"isComp":false,"url":"https://basketball.eurobasket.com/player/Emil-Grosse/520984"},{"n":"Gustav Suhr-Jessen","h":201,"p":"F","y":1998,"nat":null,"c":"BASKETBALL CLUB COPENHAGEN","co":"Denmark","coD":"Denmark","s":"free","to":null,"tl":null,"isComp":false,"url":null},{"n":"Anton Bertelsen","h":187,"p":"G","y":2006,"nat":null,"c":"BASKETBALL CLUB COPENHAGEN","co":"Denmark","coD":"Denmark","s":"free","to":null,"tl":null,"isComp":false,"url":null},{"n":"Jamie Dada","h":191,"p":"SF","y":2007,"nat":null,"c":"BASKETBALL CLUB COPENHAGEN","co":"Denmark","coD":"Denmark","s":"free","to":null,"tl":null,"isComp":false,"url":null},{"n":"David Knudsen","h":195,"p":"SG","y":1994,"nat":null,"c":"BASKETBALL CLUB COPENHAGEN","co":"Denmark","coD":"Denmark","s":"free","to":null,"tl":null,"isComp":false,"url":null},{"n":"Kasper Quvang","h":201,"p":"SF","y":2005,"nat":null,"c":"BASKETBALL CLUB COPENHAGEN","co":"Denmark","coD":"Denmark","s":"free","to":null,"tl":null,"isComp":false,"url":null},{"n":"Viggo Rimdal","h":201,"p":"F","y":2007,"nat":null,"c":"BASKETBALL CLUB COPENHAGEN","co":"Denmark","coD":"Denmark","s":"free","to":null,"tl":null,"isComp":false,"url":null},{"n":"Mathias Christensen","h":204,"p":"F","y":1995,"nat":null,"c":"BASKETBALL CLUB COPENHAGEN","co":"Denmark","coD":"Denmark","s":"free","to":null,"tl":null,"isComp":false,"url":null},{"n":"Bilal Pedersen","h":190,"p":"PG","y":2006,"nat":null,"c":"BASKETBALL CLUB COPENHAGEN","co":"Denmark","coD":"Denmark","s":"free","to":null,"tl":null,"isComp":false,"url":null},{"n":"Martin Poulsen","h":195,"p":"PG","y":1998,"nat":null,"c":"BASKETBALL CLUB COPENHAGEN","co":"Denmark","coD":"Denmark","s":"free","to":null,"tl":null,"isComp":false,"url":null},{"n":"William Vang","h":190,"p":"PG","y":2001,"nat":null,"c":"BASKETBALL CLUB COPENHAGEN","co":"Denmark","coD":"Denmark","s":"free","to":null,"tl":null,"isComp":false,"url":null},{"n":"Thomas Andersen","h":201,"p":"SF","y":2005,"nat":null,"c":"BASKETBALL CLUB COPENHAGEN","co":"Denmark","coD":"Denmark","s":"free","to":null,"tl":null,"isComp":false,"url":null},{"n":"William Bloch","h":193,"p":"G","y":2005,"nat":"Danska","c":"BEARS ACADEMY AARHUS","co":"Denmark","coD":"Denmark","s":null,"to":null,"tl":null,"isComp":false,"url":"https://basketball.eurobasket.com/player/William-Bloch/663406"},{"n":"Luka Churchill","h":198,"p":"F","y":2007,"nat":"Danska","c":"BEARS ACADEMY AARHUS","co":"Denmark","coD":"Denmark","s":null,"to":null,"tl":null,"isComp":false,"url":"https://basketball.eurobasket.com/player/Luka-Churchill/663407"},{"n":"Laurits Aaboe","h":210,"p":"F","y":2008,"nat":null,"c":"BEARS ACADEMY AARHUS","co":"Denmark","coD":"Denmark","s":"free","to":null,"tl":null,"isComp":false,"url":null},{"n":"Frederik Fruelund","h":200,"p":"F","y":2009,"nat":null,"c":"BEARS ACADEMY AARHUS","co":"Denmark","coD":"Denmark","s":"free","to":null,"tl":null,"isComp":false,"url":null},{"n":"Anton Hjort","h":201,"p":"F","y":2008,"nat":null,"c":"BEARS ACADEMY AARHUS","co":"Denmark","coD":"Denmark","s":"free","to":null,"tl":null,"isComp":false,"url":null},{"n":"Paul Schmorleiz","h":206,"p":"F","y":2006,"nat":"Nemčija","c":"BEARS ACADEMY AARHUS","co":"Denmark","coD":"Denmark","s":"free","to":null,"tl":null,"isComp":false,"url":"https://basketball.eurobasket.com/player/Paul-Schmorleiz/710599"},{"n":"Lasse Christiansen","h":205,"p":"C","y":2005,"nat":null,"c":"BEARS ACADEMY AARHUS","co":"Denmark","coD":"Denmark","s":"free","to":null,"tl":null,"isComp":false,"url":null},{"n":"Oskar Fossum","h":193,"p":"G","y":2008,"nat":null,"c":"BEARS ACADEMY AARHUS","co":"Denmark","coD":"Denmark","s":"free","to":null,"tl":null,"isComp":false,"url":null},{"n":"Mads Hansen","h":193,"p":"G","y":2002,"nat":null,"c":"BEARS ACADEMY AARHUS","co":"Denmark","coD":"Denmark","s":"free","to":null,"tl":null,"isComp":false,"url":null},{"n":"Mads Ziegler","h":187,"p":"G","y":2007,"nat":null,"c":"BEARS ACADEMY AARHUS","co":"Denmark","coD":"Denmark","s":"free","to":null,"tl":null,"isComp":false,"url":null},{"n":"Holger Rasmussen","h":204,"p":"C","y":2001,"nat":null,"c":"BEARS ACADEMY AARHUS","co":"Denmark","coD":"Denmark","s":"free","to":null,"tl":null,"isComp":false,"url":null},{"n":"Elliot Holm","h":191,"p":"G","y":2007,"nat":null,"c":"BEARS ACADEMY AARHUS","co":"Denmark","coD":"Denmark","s":"free","to":null,"tl":null,"isComp":false,"url":null},{"n":"Frederik Lauritzen","h":197,"p":"F","y":2006,"nat":null,"c":"BEARS ACADEMY AARHUS","co":"Denmark","coD":"Denmark","s":"free","to":null,"tl":null,"isComp":false,"url":null},{"n":"Carl Moller","h":203,"p":"F","y":2007,"nat":null,"c":"BEARS ACADEMY AARHUS","co":"Denmark","coD":"Denmark","s":"free","to":null,"tl":null,"isComp":false,"url":null},{"n":"Isaiah Burnett","h":195,"p":"G","y":1999,"nat":"ZDA","c":"BK AMAGER","co":"Denmark","coD":"Denmark","s":"free","to":null,"tl":null,"isComp":false,"url":"https://basketball.eurobasket.com/player/Isaiah-Burnett/450830"},{"n":"Majok Gum","h":206,"p":"C","y":2000,"nat":"Kanada","c":"BK AMAGER","co":"Denmark","coD":"Denmark","s":"free","to":null,"tl":null,"isComp":false,"url":"https://basketball.eurobasket.com/player/Majok-Gum/489303"},{"n":"Elias Mollbach","h":203,"p":"F/G","y":2003,"nat":null,"c":"BK AMAGER","co":"Denmark","coD":"Denmark","s":"free","to":null,"tl":null,"isComp":false,"url":null},{"n":"Victor Blicher","h":190,"p":"F","y":2002,"nat":null,"c":"BK AMAGER","co":"Denmark","coD":"Denmark","s":"free","to":null,"tl":null,"isComp":false,"url":null},{"n":"Linus Gron","h":206,"p":"C","y":2002,"nat":null,"c":"BK AMAGER","co":"Denmark","coD":"Denmark","s":"free","to":null,"tl":null,"isComp":false,"url":null},{"n":"Oscar Quackenbush","h":187,"p":"G","y":1999,"nat":null,"c":"BK AMAGER","co":"Denmark","coD":"Denmark","s":"free","to":null,"tl":null,"isComp":false,"url":null},{"n":"Tony Wroten","h":198,"p":"G","y":1993,"nat":"ZDA","c":"BK VEJEN 1981","co":"Denmark","coD":"Denmark","s":"free","to":null,"tl":null,"isComp":false,"url":"https://basketball.eurobasket.com/player/Tony-Wroten/182815"},{"n":"Magnus Larsen","h":207,"p":"C","y":2003,"nat":null,"c":"BK VEJEN 1981","co":"Denmark","coD":"Denmark","s":"free","to":null,"tl":null,"isComp":false,"url":null},{"n":"Neema Namdar","h":188,"p":"G","y":1997,"nat":"Iranian","c":"BK VEJEN 1981","co":"Denmark","coD":"Denmark","s":"free","to":null,"tl":null,"isComp":false,"url":"https://basketball.eurobasket.com/player/Neema-Namdar/403220"},{"n":"Marcus Obitsoe","h":200,"p":"G/F","y":2003,"nat":null,"c":"BK VEJEN 1981","co":"Denmark","coD":"Denmark","s":"free","to":null,"tl":null,"isComp":false,"url":null},{"n":"Christopher Tsamas","h":180,"p":"PG","y":2002,"nat":"Francija","c":"BK VEJEN 1981","co":"Denmark","coD":"Denmark","s":"free","to":null,"tl":null,"isComp":false,"url":"https://basketball.eurobasket.com/player/Christopher-Tsamas/598997"},{"n":"Elias Weibert","h":193,"p":"G","y":2001,"nat":"Švedska","c":"BK VEJEN 1981","co":"Denmark","coD":"Denmark","s":"free","to":null,"tl":null,"isComp":false,"url":"https://basketball.eurobasket.com/player/Elias-Weibert/506164"},{"n":"Isaiah Wright","h":191,"p":"G","y":1996,"nat":"ZDA","c":"BK VEJEN 1981","co":"Denmark","coD":"Denmark","s":"free","to":null,"tl":null,"isComp":false,"url":"https://basketball.eurobasket.com/player/Isaiah-Wright/333283"},{"n":"Mathias Stubkjaer","h":204,"p":"C","y":2004,"nat":"Danska","c":"BMS HERLEV","co":"Denmark","coD":"Denmark","s":null,"to":null,"tl":null,"isComp":false,"url":"https://basketball.eurobasket.com/player/Mathias-Stubkjaer/669668"},{"n":"Per Brandt","h":201,"p":"SF","y":2004,"nat":null,"c":"BMS HERLEV","co":"Denmark","coD":"Denmark","s":"free","to":null,"tl":null,"isComp":false,"url":null},{"n":"Wilkenson Isnord","h":204,"p":"PF","y":2000,"nat":"Bahamas","c":"BMS HERLEV","co":"Denmark","coD":"Denmark","s":"free","to":null,"tl":null,"isComp":false,"url":"https://basketball.eurobasket.com/player/Wilkenson-Isnord/521273"},{"n":"Jonas Knudsen","h":197,"p":"F","y":2007,"nat":null,"c":"BMS HERLEV","co":"Denmark","coD":"Denmark","s":"free","to":null,"tl":null,"isComp":false,"url":null},{"n":"Stevan Novovic","h":197,"p":"PG","y":2006,"nat":null,"c":"BMS HERLEV","co":"Denmark","coD":"Denmark","s":"free","to":null,"tl":null,"isComp":false,"url":null},{"n":"Darragh O'Sullivan","h":196,"p":"G/F","y":2000,"nat":"Irish","c":"BMS HERLEV","co":"Denmark","coD":"Denmark","s":"free","to":null,"tl":null,"isComp":false,"url":"https://basketball.eurobasket.com/player/Darragh-OSullivan/527365"},{"n":"Leonardo Carlino","h":198,"p":"SF","y":2000,"nat":null,"c":"BMS HERLEV","co":"Denmark","coD":"Denmark","s":"free","to":null,"tl":null,"isComp":false,"url":null},{"n":"Andreas Mortensen","h":188,"p":"SG","y":2001,"nat":null,"c":"BMS HERLEV","co":"Denmark","coD":"Denmark","s":"free","to":null,"tl":null,"isComp":false,"url":null},{"n":"Igor Bakic","h":200,"p":"F","y":2000,"nat":null,"c":"BMS HERLEV","co":"Denmark","coD":"Denmark","s":"free","to":null,"tl":null,"isComp":false,"url":null},{"n":"Silas Braikia","h":180,"p":"PG","y":2007,"nat":null,"c":"BMS HERLEV","co":"Denmark","coD":"Denmark","s":"free","to":null,"tl":null,"isComp":false,"url":null},{"n":"Carlo Urne","h":197,"p":"SG","y":2000,"nat":null,"c":"BMS HERLEV","co":"Denmark","coD":"Denmark","s":"free","to":null,"tl":null,"isComp":false,"url":null},{"n":"Niklas Petersen","h":180,"p":"G","y":2005,"nat":null,"c":"BMS HERLEV","co":"Denmark","coD":"Denmark","s":"free","to":null,"tl":null,"isComp":false,"url":null},{"n":"Lau Christoffersen","h":188,"p":"PG","y":2003,"nat":null,"c":"BMS HERLEV","co":"Denmark","coD":"Denmark","s":"free","to":null,"tl":null,"isComp":false,"url":null},{"n":"Ismail Latif","h":194,"p":"C","y":2003,"nat":null,"c":"BMS HERLEV","co":"Denmark","coD":"Denmark","s":"free","to":null,"tl":null,"isComp":false,"url":null},{"n":"Mile Nedic","h":200,"p":"PF","y":1994,"nat":null,"c":"BMS HERLEV","co":"Denmark","coD":"Denmark","s":"free","to":null,"tl":null,"isComp":false,"url":null},{"n":"Mathias Stubkjaer","h":204,"p":"C","y":2004,"nat":"Danska","c":"EBS HOLBAEK-STENHUS","co":"Denmark","coD":"Denmark","s":"left","to":"Herlev","tl":"BasketLigaen","isComp":false,"url":"https://basketball.eurobasket.com/player/Mathias-Stubkjaer/669668"},{"n":"Benjamin Vazquez","h":187,"p":"G","y":2002,"nat":"Španija","c":"EBS HOLBAEK-STENHUS","co":"Denmark","coD":"Denmark","s":"free","to":null,"tl":null,"isComp":false,"url":"https://basketball.eurobasket.com/player/Benjamin-Vazquez/619232"},{"n":"Michael Drame","h":195,"p":"F","y":1999,"nat":"Španija","c":"EBS HOLBAEK-STENHUS","co":"Denmark","coD":"Denmark","s":"free","to":null,"tl":null,"isComp":false,"url":"https://basketball.eurobasket.com/player/Michael-Drame/485150"},{"n":"Taavi Pastik","h":198,"p":"F","y":2007,"nat":"Estonija","c":"EBS HOLBAEK-STENHUS","co":"Denmark","coD":"Denmark","s":"free","to":null,"tl":null,"isComp":false,"url":"https://basketball.eurobasket.com/player/Taavi-Pastik/625860"},{"n":"Maxim Shinkarev","h":190,"p":"G","y":2003,"nat":null,"c":"EBS HOLBAEK-STENHUS","co":"Denmark","coD":"Denmark","s":"free","to":null,"tl":null,"isComp":false,"url":null},{"n":"August Heming","h":202,"p":"F","y":2004,"nat":null,"c":"EBS HOLBAEK-STENHUS","co":"Denmark","coD":"Denmark","s":"free","to":null,"tl":null,"isComp":false,"url":null},{"n":"Sebastian Dyhrberg","h":194,"p":"G","y":2005,"nat":"Švedska","c":"EBS HOLBAEK-STENHUS","co":"Denmark","coD":"Denmark","s":"free","to":null,"tl":null,"isComp":false,"url":"https://basketball.eurobasket.com/player/Sebastian-Dyhrberg/624814"},{"n":"Oskar Vanner","h":201,"p":"F","y":2003,"nat":null,"c":"EBS HOLBAEK-STENHUS","co":"Denmark","coD":"Denmark","s":"free","to":null,"tl":null,"isComp":false,"url":null},{"n":"Woody Newton","h":206,"p":"G/F","y":2001,"nat":"ZDA","c":"HORSENS IC","co":"Denmark","coD":"Denmark","s":"left","to":"Hermosillo","tl":"CIBACOPA","isComp":false,"url":"https://basketball.latinbasket.com/player/Woody-Newton/505398"},{"n":"Trejon Jacob","h":196,"p":"SG","y":1998,"nat":"ZDA","c":"HORSENS IC","co":"Denmark","coD":"Denmark","s":"free","to":null,"tl":null,"isComp":false,"url":"https://basketball.eurobasket.com/player/Trejon-Jacob/430889"},{"n":"Dario Denjalic","h":201,"p":"F","y":2007,"nat":null,"c":"HORSENS IC","co":"Denmark","coD":"Denmark","s":"free","to":null,"tl":null,"isComp":false,"url":null},{"n":"Anton Harbo","h":191,"p":"G","y":2000,"nat":null,"c":"HORSENS IC","co":"Denmark","coD":"Denmark","s":"free","to":null,"tl":null,"isComp":false,"url":null},{"n":"Matt Johnson II","h":188,"p":"G","y":1999,"nat":"ZDA","c":"HORSENS IC","co":"Denmark","coD":"Denmark","s":"free","to":null,"tl":null,"isComp":false,"url":"https://basketball.eurobasket.com/player/Matt-Johnson-II/424812"},{"n":"Magnus Madsen","h":201,"p":"PF","y":2003,"nat":null,"c":"HORSENS IC","co":"Denmark","coD":"Denmark","s":"free","to":null,"tl":null,"isComp":false,"url":null},{"n":"Kareem Reid","h":204,"p":"C","y":2000,"nat":"ZDA","c":"HORSENS IC","co":"Denmark","coD":"Denmark","s":"free","to":null,"tl":null,"isComp":false,"url":"https://basketball.eurobasket.com/player/Kareem-Reid/444888"},{"n":"Liam Sorensen","h":197,"p":"F","y":2000,"nat":null,"c":"HORSENS IC","co":"Denmark","coD":"Denmark","s":"free","to":null,"tl":null,"isComp":false,"url":null},{"n":"Marius Kirkholt","h":185,"p":"PG","y":1997,"nat":null,"c":"HORSENS IC","co":"Denmark","coD":"Denmark","s":"free","to":null,"tl":null,"isComp":false,"url":null},{"n":"Tarik Edhemovic","h":188,"p":"G","y":2004,"nat":null,"c":"HORSENS IC","co":"Denmark","coD":"Denmark","s":"free","to":null,"tl":null,"isComp":false,"url":null},{"n":"Bakir Serdarevic","h":193,"p":"SG","y":2000,"nat":"Danska","c":"RANDERS CIMBRIA BASKETBALL","co":"Denmark","coD":"Denmark","s":null,"to":null,"tl":null,"isComp":false,"url":"https://basketball.eurobasket.com/player/Bakir-Serdarevic/393630"},{"n":"Adama Darboe","h":190,"p":"G","y":1986,"nat":null,"c":"RANDERS CIMBRIA BASKETBALL","co":"Denmark","coD":"Denmark","s":"free","to":null,"tl":null,"isComp":false,"url":null},{"n":"Josh Fortune","h":196,"p":"SG","y":1994,"nat":"ZDA","c":"RANDERS CIMBRIA BASKETBALL","co":"Denmark","coD":"Denmark","s":"free","to":null,"tl":null,"isComp":false,"url":"https://basketball.eurobasket.com/player/Josh-Fortune/266306"},{"n":"Asger Lillebaek","h":null,"p":null,"y":2008,"nat":null,"c":"RANDERS CIMBRIA BASKETBALL","co":"Denmark","coD":"Denmark","s":"free","to":null,"tl":null,"isComp":false,"url":null},{"n":"Xander Rice","h":190,"p":"G","y":2001,"nat":"ZDA","c":"RANDERS CIMBRIA BASKETBALL","co":"Denmark","coD":"Denmark","s":"free","to":null,"tl":null,"isComp":false,"url":"https://basketball.eurobasket.com/player/Xander-Rice/518796"},{"n":"Morten Bulow","h":204,"p":"C/F","y":1999,"nat":null,"c":"RANDERS CIMBRIA BASKETBALL","co":"Denmark","coD":"Denmark","s":"free","to":null,"tl":null,"isComp":false,"url":null},{"n":"Gustav Ronneholt","h":197,"p":"F","y":2000,"nat":null,"c":"RANDERS CIMBRIA BASKETBALL","co":"Denmark","coD":"Denmark","s":"free","to":null,"tl":null,"isComp":false,"url":null},{"n":"Sharif Barfi","h":198,"p":"PG","y":2004,"nat":null,"c":"RANDERS CIMBRIA BASKETBALL","co":"Denmark","coD":"Denmark","s":"free","to":null,"tl":null,"isComp":false,"url":null},{"n":"Gustav Johansen","h":201,"p":"F","y":2000,"nat":null,"c":"RANDERS CIMBRIA BASKETBALL","co":"Denmark","coD":"Denmark","s":"free","to":null,"tl":null,"isComp":false,"url":null},{"n":"Oliver Barker","h":181,"p":"G","y":2004,"nat":null,"c":"RANDERS CIMBRIA BASKETBALL","co":"Denmark","coD":"Denmark","s":"free","to":null,"tl":null,"isComp":false,"url":null},{"n":"Oscar Alm","h":195,"p":"F","y":2000,"nat":null,"c":"RANDERS CIMBRIA BASKETBALL","co":"Denmark","coD":"Denmark","s":"free","to":null,"tl":null,"isComp":false,"url":null},{"n":"Anton Lonstrup","h":187,"p":"G","y":2000,"nat":null,"c":"RANDERS CIMBRIA BASKETBALL","co":"Denmark","coD":"Denmark","s":"free","to":null,"tl":null,"isComp":false,"url":null},{"n":"Adam Heede-Andersen","h":187,"p":"G","y":1996,"nat":null,"c":"SVENDBORG RABBITS","co":"Denmark","coD":"Denmark","s":"free","to":null,"tl":null,"isComp":false,"url":null},{"n":"Akuel Kot","h":188,"p":"G","y":2001,"nat":"South Sudanese","c":"SVENDBORG RABBITS","co":"Denmark","coD":"Denmark","s":"free","to":null,"tl":null,"isComp":false,"url":"https://basketball.eurobasket.com/player/Akuel-Kot/520611"},{"n":"Jay Nagle","h":206,"p":"F","y":2000,"nat":"ZDA","c":"SVENDBORG RABBITS","co":"Denmark","coD":"Denmark","s":"free","to":null,"tl":null,"isComp":false,"url":"https://basketball.eurobasket.com/player/Jay-Nagle/475805"},{"n":"Balsa Veljic","h":184,"p":"PG","y":2000,"nat":null,"c":"SVENDBORG RABBITS","co":"Denmark","coD":"Denmark","s":"free","to":null,"tl":null,"isComp":false,"url":null},{"n":"David Hockerup-Fischer","h":208,"p":"C","y":2001,"nat":"Danska","c":"SVENDBORG RABBITS","co":"Denmark","coD":"Denmark","s":"free","to":null,"tl":null,"isComp":false,"url":"https://basketball.eurobasket.com/player/David-Hockerup-Fischer/478415"},{"n":"Magnus Sorensen","h":196,"p":"G","y":2007,"nat":null,"c":"SVENDBORG RABBITS","co":"Denmark","coD":"Denmark","s":"free","to":null,"tl":null,"isComp":false,"url":null},{"n":"Tyrese Dada","h":197,"p":"G","y":2005,"nat":null,"c":"SVENDBORG RABBITS","co":"Denmark","coD":"Denmark","s":"free","to":null,"tl":null,"isComp":false,"url":null},{"n":"Gabriel Vogel","h":199,"p":"F","y":2005,"nat":null,"c":"SVENDBORG RABBITS","co":"Denmark","coD":"Denmark","s":"free","to":null,"tl":null,"isComp":false,"url":null},{"n":"Cole Bajema","h":201,"p":"G","y":2000,"nat":"ZDA","c":"TEAM FOG NAESTVED","co":"Denmark","coD":"Denmark","s":"free","to":null,"tl":null,"isComp":false,"url":"https://basketball.eurobasket.com/player/Cole-Bajema/502654"},{"n":"Pipeloluwa Ajayi","h":201,"p":"F","y":2003,"nat":"Kanada","c":"TEAM FOG NAESTVED","co":"Denmark","coD":"Denmark","s":"free","to":null,"tl":null,"isComp":false,"url":"https://basketball.eurobasket.com/player/Pipeloluwa-Ajayi/626709"},{"n":"Frederik Bak","h":198,"p":"F","y":2006,"nat":null,"c":"TEAM FOG NAESTVED","co":"Denmark","coD":"Denmark","s":"free","to":null,"tl":null,"isComp":false,"url":null},{"n":"Tyler Harris","h":175,"p":"PG","y":1998,"nat":"ZDA","c":"TEAM FOG NAESTVED","co":"Denmark","coD":"Denmark","s":"free","to":null,"tl":null,"isComp":false,"url":"https://basketball.eurobasket.com/player/Tyler-Harris/457217"},{"n":"Ikenna Okeke","h":198,"p":"G","y":2001,"nat":"Nigerija","c":"TEAM FOG NAESTVED","co":"Denmark","coD":"Denmark","s":"free","to":null,"tl":null,"isComp":false,"url":"https://basketball.eurobasket.com/player/Ikenna-Okeke/545937"},{"n":"Rollie Worster","h":193,"p":"G","y":2000,"nat":"ZDA","c":"TEAM FOG NAESTVED","co":"Denmark","coD":"Denmark","s":"free","to":null,"tl":null,"isComp":false,"url":"https://basketball.eurobasket.com/player/Rollie-Worster/526929"},{"n":"David Jean-Baptiste","h":195,"p":"G","y":1998,"nat":"Haitian","c":"TEAM FOG NAESTVED","co":"Denmark","coD":"Denmark","s":"free","to":null,"tl":null,"isComp":false,"url":"https://basketball.eurobasket.com/player/David-Jean-Baptiste/402390"},{"n":"Lukas Christensen","h":190,"p":"G","y":2006,"nat":null,"c":"TEAM FOG NAESTVED","co":"Denmark","coD":"Denmark","s":"free","to":null,"tl":null,"isComp":false,"url":null},{"n":"Magnus Donsrud","h":204,"p":"F","y":2004,"nat":null,"c":"VAERLOSE BLUE HAWKS","co":"Denmark","coD":"Denmark","s":"free","to":null,"tl":null,"isComp":false,"url":null},{"n":"Gustav Erichsen","h":197,"p":"G","y":2009,"nat":null,"c":"VAERLOSE BLUE HAWKS","co":"Denmark","coD":"Denmark","s":"free","to":null,"tl":null,"isComp":false,"url":null},{"n":"Thorgrimur Halldorsson","h":208,"p":"C/F","y":2003,"nat":"Islandija","c":"VAERLOSE BLUE HAWKS","co":"Denmark","coD":"Denmark","s":"free","to":null,"tl":null,"isComp":false,"url":"https://basketball.eurobasket.com/player/Thorgrimur-Halldorsson/622448"},{"n":"Jakob Johansson","h":194,"p":"F","y":2005,"nat":null,"c":"VAERLOSE BLUE HAWKS","co":"Denmark","coD":"Denmark","s":"free","to":null,"tl":null,"isComp":false,"url":null},{"n":"Ogbemudia Uagboe","h":192,"p":"G","y":2005,"nat":null,"c":"VAERLOSE BLUE HAWKS","co":"Denmark","coD":"Denmark","s":"free","to":null,"tl":null,"isComp":false,"url":null},{"n":"Willas Moller","h":196,"p":"SG","y":2006,"nat":null,"c":"VAERLOSE BLUE HAWKS","co":"Denmark","coD":"Denmark","s":"free","to":null,"tl":null,"isComp":false,"url":null},{"n":"Jonas Van Meurs","h":199,"p":"G","y":2005,"nat":null,"c":"VAERLOSE BLUE HAWKS","co":"Denmark","coD":"Denmark","s":"free","to":null,"tl":null,"isComp":false,"url":null},{"n":"Peter Bachmann","h":200,"p":"C/F","y":2002,"nat":null,"c":"VAERLOSE BLUE HAWKS","co":"Denmark","coD":"Denmark","s":"free","to":null,"tl":null,"isComp":false,"url":null},{"n":"Noah Baker","h":184,"p":"G","y":2003,"nat":null,"c":"VAERLOSE BLUE HAWKS","co":"Denmark","coD":"Denmark","s":"free","to":null,"tl":null,"isComp":false,"url":null},{"n":"Hannibal Offenberg","h":201,"p":"F","y":2004,"nat":null,"c":"VAERLOSE BLUE HAWKS","co":"Denmark","coD":"Denmark","s":"free","to":null,"tl":null,"isComp":false,"url":null},{"n":"Thomas Brodie","h":190,"p":"G","y":2005,"nat":null,"c":"VAERLOSE BLUE HAWKS","co":"Denmark","coD":"Denmark","s":"free","to":null,"tl":null,"isComp":false,"url":null},{"n":"Silas Ilkjaer","h":200,"p":"F","y":1999,"nat":null,"c":"VAERLOSE BLUE HAWKS","co":"Denmark","coD":"Denmark","s":"free","to":null,"tl":null,"isComp":false,"url":null}]}