{"co":"Latvia","coD":"Latvia","players":[{"n":"Kristians Feierbergs","h":203,"p":"F","y":2002,"nat":"Latvija","c":"BK LIEPAJA","co":"Latvia","coD":"Latvia","s":"left","to":"Rigas Z.","tl":"LBL","isComp":false,"url":"https://basketball.eurobasket.com/player/Kristians-Feierbergs/449294"},{"n":"Edvards Egle","h":190,"p":"SG","y":2005,"nat":null,"c":"BK LIEPAJA","co":"Latvia","coD":"Latvia","s":"free","to":null,"tl":null,"isComp":false,"url":null},{"n":"Edvards Jonaitis","h":164,"p":"PG","y":2008,"nat":null,"c":"BK LIEPAJA","co":"Latvia","coD":"Latvia","s":"free","to":null,"tl":null,"isComp":false,"url":null},{"n":"Emils Krumins","h":185,"p":"PG","y":2001,"nat":null,"c":"BK LIEPAJA","co":"Latvia","coD":"Latvia","s":"free","to":null,"tl":null,"isComp":false,"url":null},{"n":"Reds Martinsons","h":177,"p":"PG","y":2007,"nat":null,"c":"BK LIEPAJA","co":"Latvia","coD":"Latvia","s":"free","to":null,"tl":null,"isComp":false,"url":null},{"n":"Matiss Ozolins-Pese","h":190,"p":"SF","y":2008,"nat":null,"c":"BK LIEPAJA","co":"Latvia","coD":"Latvia","s":"free","to":null,"tl":null,"isComp":false,"url":null},{"n":"Helmuts Petrovics","h":198,"p":"PG","y":2007,"nat":null,"c":"BK LIEPAJA","co":"Latvia","coD":"Latvia","s":"free","to":null,"tl":null,"isComp":false,"url":null},{"n":"Vitalii Shymanskyi","h":205,"p":"PF","y":2003,"nat":"Ukrajina","c":"BK LIEPAJA","co":"Latvia","coD":"Latvia","s":"free","to":null,"tl":null,"isComp":false,"url":"https://basketball.eurobasket.com/player/Vitalii-Shymanskyi/493310"},{"n":"Rinalds Timma","h":193,"p":"G","y":2003,"nat":null,"c":"BK LIEPAJA","co":"Latvia","coD":"Latvia","s":"free","to":null,"tl":null,"isComp":false,"url":null},{"n":"Edgars Liekis","h":213,"p":"C","y":2002,"nat":null,"c":"BK LIEPAJA","co":"Latvia","coD":"Latvia","s":"free","to":null,"tl":null,"isComp":false,"url":null},{"n":"Kristians Sulcs","h":193,"p":"SG","y":2002,"nat":"Latvija","c":"BK LIEPAJA","co":"Latvia","coD":"Latvia","s":"free","to":null,"tl":null,"isComp":false,"url":"https://basketball.eurobasket.com/player/Kristians-Sulcs/448671"},{"n":"Henriks Bajars","h":213,"p":"C","y":2002,"nat":null,"c":"BK LIEPAJA","co":"Latvia","coD":"Latvia","s":"free","to":null,"tl":null,"isComp":false,"url":null},{"n":"Karlis Apsitis","h":200,"p":"SF","y":1992,"nat":"Latvija","c":"BK OGRE","co":"Latvia","coD":"Latvia","s":null,"to":null,"tl":null,"isComp":false,"url":"https://basketball.eurobasket.com/player/Karlis-Apsitis/159855"},{"n":"Justin Ndjock-Tadjore","h":203,"p":"F","y":2001,"nat":"Kanada","c":"BK OGRE","co":"Latvia","coD":"Latvia","s":"left","to":"Ottawa","tl":"CEBL","isComp":false,"url":"https://basketball.usbasket.com/player/Justin-Ndjock-Tadjore/509292"},{"n":"Keishawn Davidson","h":188,"p":"G","y":2001,"nat":"ZDA","c":"BK OGRE","co":"Latvia","coD":"Latvia","s":"free","to":null,"tl":null,"isComp":false,"url":"https://basketball.eurobasket.com/player/Keishawn-Davidson/500607"},{"n":"Luka Hlebovickis","h":179,"p":"G","y":2009,"nat":null,"c":"BK OGRE","co":"Latvia","coD":"Latvia","s":"free","to":null,"tl":null,"isComp":false,"url":null},{"n":"Martins Kudrjavcevs","h":197,"p":"SF","y":2009,"nat":null,"c":"BK OGRE","co":"Latvia","coD":"Latvia","s":"free","to":null,"tl":null,"isComp":false,"url":null},{"n":"Anders Nelson","h":185,"p":"PG","y":1999,"nat":"ZDA","c":"BK OGRE","co":"Latvia","coD":"Latvia","s":"free","to":null,"tl":null,"isComp":false,"url":"https://basketball.eurobasket.com/player/Anders-Nelson/496671"},{"n":"Marlon Short","h":193,"p":"G","y":2001,"nat":"ZDA","c":"BK OGRE","co":"Latvia","coD":"Latvia","s":"free","to":null,"tl":null,"isComp":false,"url":"https://basketball.eurobasket.com/player/Marlon-Short/565059"},{"n":"Aleks Simsons","h":176,"p":"G","y":2006,"nat":null,"c":"BK OGRE","co":"Latvia","coD":"Latvia","s":"free","to":null,"tl":null,"isComp":false,"url":null},{"n":"Reinis Avotins","h":205,"p":"C","y":1998,"nat":null,"c":"BK OGRE","co":"Latvia","coD":"Latvia","s":"free","to":null,"tl":null,"isComp":false,"url":null},{"n":"Kaspars Berzins","h":213,"p":"C","y":1985,"nat":null,"c":"BK OGRE","co":"Latvia","coD":"Latvia","s":"free","to":null,"tl":null,"isComp":false,"url":null},{"n":"Anatoliy Shundel","h":192,"p":"SG","y":1993,"nat":"Ukrajina","c":"BK OGRE","co":"Latvia","coD":"Latvia","s":"free","to":null,"tl":null,"isComp":false,"url":"https://basketball.eurobasket.com/player/Anatoliy-Shundel/197259"},{"n":"Guntis Sipolins","h":207,"p":"PF","y":1993,"nat":null,"c":"BK OGRE","co":"Latvia","coD":"Latvia","s":"free","to":null,"tl":null,"isComp":false,"url":null},{"n":"Gustavs Kampuss","h":188,"p":"SG","y":1999,"nat":null,"c":"BK OGRE","co":"Latvia","coD":"Latvia","s":"free","to":null,"tl":null,"isComp":false,"url":null},{"n":"Volodymyr Poluiakhtov","h":204,"p":"F","y":2004,"nat":"Ukrajina","c":"BK OGRE","co":"Latvia","coD":"Latvia","s":"free","to":null,"tl":null,"isComp":false,"url":"https://basketball.eurobasket.com/player/Volodymyr-Poluiakhtov/537924"},{"n":"Kristaps Dargais","h":198,"p":"PF","y":1990,"nat":"Latvija","c":"BK OGRE","co":"Latvia","coD":"Latvia","s":"free","to":null,"tl":null,"isComp":false,"url":"https://basketball.eurobasket.com/player/Kristaps-Dargais/199816"},{"n":"Markuss Lastins","h":195,"p":"SG","y":2004,"nat":null,"c":"BK OGRE","co":"Latvia","coD":"Latvia","s":"free","to":null,"tl":null,"isComp":false,"url":null},{"n":"Nikolajs Atanasovs","h":201,"p":"F","y":2001,"nat":null,"c":"BK VENTSPILS","co":"Latvia","coD":"Latvia","s":"free","to":null,"tl":null,"isComp":false,"url":null},{"n":"Aaron Johnson-Cash","h":198,"p":"G","y":1998,"nat":"ZDA","c":"BK VENTSPILS","co":"Latvia","coD":"Latvia","s":"free","to":null,"tl":null,"isComp":false,"url":"https://basketball.eurobasket.com/player/Aaron-Johnson-Cash/598571"},{"n":"Cameron Shelton","h":188,"p":"G","y":1999,"nat":"ZDA","c":"BK VENTSPILS","co":"Latvia","coD":"Latvia","s":"free","to":null,"tl":null,"isComp":false,"url":"https://basketball.eurobasket.com/player/Cameron-Shelton/424289"},{"n":"Rihards Teirumnieks","h":185,"p":"SF","y":2003,"nat":"Latvija","c":"BK VENTSPILS","co":"Latvia","coD":"Latvia","s":"free","to":null,"tl":null,"isComp":false,"url":"https://basketball.eurobasket.com/player/Rihards-Teirumnieks/471848"},{"n":"Bryant Thomas","h":203,"p":"C","y":1999,"nat":"ZDA","c":"BK VENTSPILS","co":"Latvia","coD":"Latvia","s":"free","to":null,"tl":null,"isComp":false,"url":"https://basketball.eurobasket.com/player/Bryant-Thomas/447176"},{"n":"Amandas Urkis","h":199,"p":"F","y":1999,"nat":"Litva","c":"BK VENTSPILS","co":"Latvia","coD":"Latvia","s":"free","to":null,"tl":null,"isComp":false,"url":"https://basketball.eurobasket.com/player/Amandas-Urkis/385012"},{"n":"Roberts Berze","h":198,"p":"F","y":2001,"nat":null,"c":"BK VENTSPILS","co":"Latvia","coD":"Latvia","s":"free","to":null,"tl":null,"isComp":false,"url":null},{"n":"Karlis Skilins","h":201,"p":"PF","y":2007,"nat":null,"c":"BK VENTSPILS","co":"Latvia","coD":"Latvia","s":"free","to":null,"tl":null,"isComp":false,"url":null},{"n":"Renars Birkans","h":186,"p":"PG","y":1997,"nat":null,"c":"BK VENTSPILS","co":"Latvia","coD":"Latvia","s":"free","to":null,"tl":null,"isComp":false,"url":null},{"n":"Janis Censonis","h":185,"p":"G","y":2005,"nat":null,"c":"BK VENTSPILS","co":"Latvia","coD":"Latvia","s":"free","to":null,"tl":null,"isComp":false,"url":null},{"n":"Edvards Mezulis","h":202,"p":"C","y":2000,"nat":null,"c":"BK VENTSPILS","co":"Latvia","coD":"Latvia","s":"free","to":null,"tl":null,"isComp":false,"url":null},{"n":"Ronalds Zakis","h":207,"p":"C","y":1987,"nat":null,"c":"BK VENTSPILS","co":"Latvia","coD":"Latvia","s":"free","to":null,"tl":null,"isComp":false,"url":null},{"n":"Arturs Ausejs","h":192,"p":"SG","y":1990,"nat":null,"c":"BK VENTSPILS","co":"Latvia","coD":"Latvia","s":"free","to":null,"tl":null,"isComp":false,"url":null},{"n":"Tristan Jarrett","h":193,"p":"G","y":1998,"nat":"ZDA","c":"LATVIJAS UNIVERSITATE","co":"Latvia","coD":"Latvia","s":"left","to":"Soles","tl":"LNB","isComp":false,"url":"https://basketball.latinbasket.com/player/Tristan-Jarrett/424927"},{"n":"Oto Bergmanis","h":178,"p":"PG","y":2007,"nat":null,"c":"LATVIJAS UNIVERSITATE","co":"Latvia","coD":"Latvia","s":"free","to":null,"tl":null,"isComp":false,"url":null},{"n":"Rudis Donis","h":200,"p":"PF","y":2006,"nat":null,"c":"LATVIJAS UNIVERSITATE","co":"Latvia","coD":"Latvia","s":"free","to":null,"tl":null,"isComp":false,"url":null},{"n":"Verners Drava","h":201,"p":"SG","y":2006,"nat":null,"c":"LATVIJAS UNIVERSITATE","co":"Latvia","coD":"Latvia","s":"free","to":null,"tl":null,"isComp":false,"url":null},{"n":"Brody Fox","h":198,"p":"F","y":2002,"nat":"ZDA","c":"LATVIJAS UNIVERSITATE","co":"Latvia","coD":"Latvia","s":"free","to":null,"tl":null,"isComp":false,"url":"https://basketball.eurobasket.com/player/Brody-Fox/591419"},{"n":"Kristaps Gluditis","h":190,"p":"SG","y":1995,"nat":null,"c":"LATVIJAS UNIVERSITATE","co":"Latvia","coD":"Latvia","s":"free","to":null,"tl":null,"isComp":false,"url":null},{"n":"Davids Grinbergs","h":203,"p":"F","y":2003,"nat":null,"c":"LATVIJAS UNIVERSITATE","co":"Latvia","coD":"Latvia","s":"free","to":null,"tl":null,"isComp":false,"url":null},{"n":"Pauls Katlaps","h":188,"p":"G","y":2006,"nat":null,"c":"LATVIJAS UNIVERSITATE","co":"Latvia","coD":"Latvia","s":"free","to":null,"tl":null,"isComp":false,"url":null},{"n":"Arturs Kazaks","h":190,"p":"SG","y":2005,"nat":null,"c":"LATVIJAS UNIVERSITATE","co":"Latvia","coD":"Latvia","s":"free","to":null,"tl":null,"isComp":false,"url":null},{"n":"Francis Neilands","h":194,"p":"PG","y":2005,"nat":null,"c":"LATVIJAS UNIVERSITATE","co":"Latvia","coD":"Latvia","s":"free","to":null,"tl":null,"isComp":false,"url":null},{"n":"Timurs Peiners","h":161,"p":"G","y":2006,"nat":null,"c":"LATVIJAS UNIVERSITATE","co":"Latvia","coD":"Latvia","s":"free","to":null,"tl":null,"isComp":false,"url":null},{"n":"Martins Piternieks","h":185,"p":"G","y":2006,"nat":null,"c":"LATVIJAS UNIVERSITATE","co":"Latvia","coD":"Latvia","s":"free","to":null,"tl":null,"isComp":false,"url":null},{"n":"Zion Styles","h":190,"p":"G","y":2000,"nat":"ZDA","c":"LATVIJAS UNIVERSITATE","co":"Latvia","coD":"Latvia","s":"free","to":null,"tl":null,"isComp":false,"url":"https://basketball.eurobasket.com/player/Zion-Styles/504339"},{"n":"Ralfs Tumasevs","h":199,"p":"SF","y":2004,"nat":null,"c":"LATVIJAS UNIVERSITATE","co":"Latvia","coD":"Latvia","s":"free","to":null,"tl":null,"isComp":false,"url":null},{"n":"Harijs Kaupmanis","h":200,"p":"F","y":2005,"nat":null,"c":"LATVIJAS UNIVERSITATE","co":"Latvia","coD":"Latvia","s":"free","to":null,"tl":null,"isComp":false,"url":null},{"n":"Daniils Smirnovs","h":204,"p":"PF","y":2003,"nat":"Estonija","c":"LATVIJAS UNIVERSITATE","co":"Latvia","coD":"Latvia","s":"free","to":null,"tl":null,"isComp":false,"url":"https://basketball.eurobasket.com/player/Daniils-Smirnovs/632338"},{"n":"Andrejs Bikovs","h":216,"p":"C","y":2003,"nat":null,"c":"LATVIJAS UNIVERSITATE","co":"Latvia","coD":"Latvia","s":"free","to":null,"tl":null,"isComp":false,"url":null},{"n":"Edvards Lucis","h":185,"p":"SG","y":2000,"nat":null,"c":"LATVIJAS UNIVERSITATE","co":"Latvia","coD":"Latvia","s":"free","to":null,"tl":null,"isComp":false,"url":null},{"n":"Kristians Feierbergs","h":203,"p":"F","y":2002,"nat":"Latvija","c":"RIGAS ZELLI","co":"Latvia","coD":"Latvia","s":null,"to":null,"tl":null,"isComp":false,"url":"https://basketball.eurobasket.com/player/Kristians-Feierbergs/449294"},{"n":"Kristers Kikusts","h":180,"p":"G","y":2007,"nat":"Latvija","c":"RIGAS ZELLI","co":"Latvia","coD":"Latvia","s":null,"to":null,"tl":null,"isComp":false,"url":"https://basketball.eurobasket.com/player/Kristers-Kikusts/698163"},{"n":"Enzo Abele","h":195,"p":"G","y":2007,"nat":null,"c":"RIGAS ZELLI","co":"Latvia","coD":"Latvia","s":"free","to":null,"tl":null,"isComp":false,"url":null},{"n":"Christian Anigwe","h":206,"p":"F","y":2000,"nat":"ZDA","c":"RIGAS ZELLI","co":"Latvia","coD":"Latvia","s":"free","to":null,"tl":null,"isComp":false,"url":"https://basketball.eurobasket.com/player/Christian-Anigwe/424272"},{"n":"Janis Berzins","h":201,"p":"F","y":1993,"nat":null,"c":"RIGAS ZELLI","co":"Latvia","coD":"Latvia","s":"free","to":null,"tl":null,"isComp":false,"url":null},{"n":"Frankie Fidler","h":201,"p":"F","y":2003,"nat":"ZDA","c":"RIGAS ZELLI","co":"Latvia","coD":"Latvia","s":"free","to":null,"tl":null,"isComp":false,"url":"https://basketball.eurobasket.com/player/Frankie-Fidler/571829"},{"n":"Jackie Johnson III","h":180,"p":"PG","y":2002,"nat":"ZDA","c":"RIGAS ZELLI","co":"Latvia","coD":"Latvia","s":"free","to":null,"tl":null,"isComp":false,"url":"https://basketball.eurobasket.com/player/Jackie-Johnson-III/518856"},{"n":"Denis Krestinin","h":202,"p":"F","y":1994,"nat":"Litva","c":"RIGAS ZELLI","co":"Latvia","coD":"Latvia","s":"free","to":null,"tl":null,"isComp":false,"url":"https://basketball.eurobasket.com/player/Denis-Krestinin/187727"},{"n":"Raivo Kudrjavcevs","h":194,"p":"G","y":2008,"nat":null,"c":"RIGAS ZELLI","co":"Latvia","coD":"Latvia","s":"free","to":null,"tl":null,"isComp":false,"url":null},{"n":"Denys Lukashov","h":188,"p":"PG","y":1989,"nat":"Ukrajina","c":"RIGAS ZELLI","co":"Latvia","coD":"Latvia","s":"free","to":null,"tl":null,"isComp":false,"url":"https://basketball.eurobasket.com/player/Denys-Lukashov/78268"},{"n":"Rodijs Macoha","h":200,"p":"F","y":2002,"nat":null,"c":"RIGAS ZELLI","co":"Latvia","coD":"Latvia","s":"free","to":null,"tl":null,"isComp":false,"url":null},{"n":"Ritvars Nikolajevs","h":188,"p":"G","y":2007,"nat":null,"c":"RIGAS ZELLI","co":"Latvia","coD":"Latvia","s":"free","to":null,"tl":null,"isComp":false,"url":null},{"n":"Khalil Shabazz","h":183,"p":"PG","y":1998,"nat":"ZDA","c":"RIGAS ZELLI","co":"Latvia","coD":"Latvia","s":"free","to":null,"tl":null,"isComp":false,"url":"https://basketball.eurobasket.com/player/Khalil-Shabazz/452688"},{"n":"Roberts Berzins","h":193,"p":"SG","y":2001,"nat":"Latvija","c":"RIGAS ZELLI","co":"Latvia","coD":"Latvia","s":"free","to":null,"tl":null,"isComp":false,"url":"https://basketball.eurobasket.com/player/Roberts-Berzins/401937"},{"n":"Rolands Sulcs","h":193,"p":"PG","y":2006,"nat":null,"c":"RIGAS ZELLI","co":"Latvia","coD":"Latvia","s":"free","to":null,"tl":null,"isComp":false,"url":null},{"n":"Ugis Pinete","h":194,"p":"PG","y":1991,"nat":null,"c":"RIGAS ZELLI","co":"Latvia","coD":"Latvia","s":"free","to":null,"tl":null,"isComp":false,"url":null},{"n":"Juris Vitols","h":188,"p":"PG","y":2005,"nat":null,"c":"RIGAS ZELLI","co":"Latvia","coD":"Latvia","s":"free","to":null,"tl":null,"isComp":false,"url":null},{"n":"Omar Pajic","h":205,"p":"C","y":1999,"nat":"BiH","c":"RIGAS ZELLI","co":"Latvia","coD":"Latvia","s":"left","to":"Goettingen","tl":"ProA","isComp":false,"url":"https://basketball.eurobasket.com/player/Omar-Pajic/481066"},{"n":"Arnis Ate","h":182,"p":"PG","y":1994,"nat":null,"c":"RIGAS ZELLI","co":"Latvia","coD":"Latvia","s":"free","to":null,"tl":null,"isComp":false,"url":null},{"n":"Pavlo Dziuba","h":203,"p":"F","y":2003,"nat":"Ukrajina","c":"RIGAS ZELLI","co":"Latvia","coD":"Latvia","s":"free","to":null,"tl":null,"isComp":false,"url":"https://basketball.eurobasket.com/player/Pavlo-Dziuba/524430"},{"n":"Janis Kalnins","h":195,"p":"SF","y":2007,"nat":null,"c":"RIGAS ZELLI","co":"Latvia","coD":"Latvia","s":"free","to":null,"tl":null,"isComp":false,"url":null},{"n":"Krists Ozers","h":192,"p":"G","y":2008,"nat":null,"c":"RIGAS ZELLI","co":"Latvia","coD":"Latvia","s":"free","to":null,"tl":null,"isComp":false,"url":null},{"n":"A.J. Pacher","h":208,"p":"F/C","y":1992,"nat":"ZDA","c":"RIGAS ZELLI","co":"Latvia","coD":"Latvia","s":"free","to":null,"tl":null,"isComp":false,"url":"https://basketball.eurobasket.com/player/AJ-Pacher/209778"},{"n":"Markuss Sipko","h":190,"p":"PG","y":2007,"nat":null,"c":"RIGAS ZELLI","co":"Latvia","coD":"Latvia","s":"free","to":null,"tl":null,"isComp":false,"url":null},{"n":"Dominykas Stenionis","h":178,"p":"PG","y":2002,"nat":"Litva","c":"RIGAS ZELLI","co":"Latvia","coD":"Latvia","s":"free","to":null,"tl":null,"isComp":false,"url":"https://basketball.eurobasket.com/player/Dominykas-Stenionis/528273"},{"n":"Aniwaniwa Tait-Jones","h":198,"p":"G/F","y":2001,"nat":"New Zealand","c":"RIGAS ZELLI","co":"Latvia","coD":"Latvia","s":"free","to":null,"tl":null,"isComp":false,"url":"https://basketball.eurobasket.com/player/Aniwaniwa-Tait-Jones/513339"},{"n":"Marcis Vitols","h":186,"p":"PG","y":1992,"nat":null,"c":"RIGAS ZELLI","co":"Latvia","coD":"Latvia","s":"free","to":null,"tl":null,"isComp":false,"url":null},{"n":"Artis Ate","h":195,"p":"SF","y":1989,"nat":null,"c":"RIGAS ZELLI","co":"Latvia","coD":"Latvia","s":"free","to":null,"tl":null,"isComp":false,"url":null},{"n":"Verners Kohs","h":203,"p":"PF","y":1997,"nat":null,"c":"RIGAS ZELLI","co":"Latvia","coD":"Latvia","s":"free","to":null,"tl":null,"isComp":false,"url":null},{"n":"Davis Ozers","h":193,"p":"SF","y":2004,"nat":null,"c":"RIGAS ZELLI","co":"Latvia","coD":"Latvia","s":"free","to":null,"tl":null,"isComp":false,"url":null},{"n":"Kristofers Karlsons","h":185,"p":"PG","y":2004,"nat":null,"c":"RIGAS ZELLI","co":"Latvia","coD":"Latvia","s":"free","to":null,"tl":null,"isComp":false,"url":null},{"n":"Curtis Hollis","h":198,"p":"SF","y":1998,"nat":"ZDA","c":"VEF RIGA","co":"Latvia","coD":"Latvia","s":"left","to":"Niagara","tl":"CEBL","isComp":false,"url":"https://basketball.usbasket.com/player/Curtis-Hollis/424720"},{"n":"Adrians Andzevs","h":191,"p":"PG","y":2007,"nat":null,"c":"VEF RIGA","co":"Latvia","coD":"Latvia","s":"free","to":null,"tl":null,"isComp":false,"url":null},{"n":"Raivo Butirins","h":206,"p":"PF","y":2003,"nat":null,"c":"VEF RIGA","co":"Latvia","coD":"Latvia","s":"free","to":null,"tl":null,"isComp":false,"url":null},{"n":"Brandon Huffman","h":208,"p":"C","y":1998,"nat":"ZDA","c":"VEF RIGA","co":"Latvia","coD":"Latvia","s":"free","to":null,"tl":null,"isComp":false,"url":"https://basketball.eurobasket.com/player/Brandon-Huffman/424695"},{"n":"Kristaps Kilps","h":195,"p":"SF","y":2001,"nat":"Latvija","c":"VEF RIGA","co":"Latvia","coD":"Latvia","s":"free","to":null,"tl":null,"isComp":false,"url":"https://basketball.eurobasket.com/player/Kristaps-Kilps/408476"},{"n":"Jekabs Niedra","h":184,"p":"G","y":2006,"nat":null,"c":"VEF RIGA","co":"Latvia","coD":"Latvia","s":"free","to":null,"tl":null,"isComp":false,"url":null},{"n":"Rostyslav Novitskyi","h":204,"p":"PF","y":2000,"nat":"Ukrajina","c":"VEF RIGA","co":"Latvia","coD":"Latvia","s":"free","to":null,"tl":null,"isComp":false,"url":"https://basketball.eurobasket.com/player/Rostyslav-Novitskyi/448291"},{"n":"Toni Rocak","h":206,"p":"F","y":1999,"nat":"Hrvaška","c":"VEF RIGA","co":"Latvia","coD":"Latvia","s":"free","to":null,"tl":null,"isComp":false,"url":"https://basketball.eurobasket.com/player/Toni-Rocak/410632"},{"n":"Kamau Stokes","h":183,"p":"PG","y":1995,"nat":"ZDA","c":"VEF RIGA","co":"Latvia","coD":"Latvia","s":"free","to":null,"tl":null,"isComp":false,"url":"https://basketball.eurobasket.com/player/Kamau-Stokes/369494"},{"n":"Ricards Vanags","h":204,"p":"SF","y":2002,"nat":null,"c":"VEF RIGA","co":"Latvia","coD":"Latvia","s":"free","to":null,"tl":null,"isComp":false,"url":null},{"n":"Rihards Aleksandrovs","h":201,"p":"PF","y":2002,"nat":null,"c":"VEF RIGA","co":"Latvia","coD":"Latvia","s":"free","to":null,"tl":null,"isComp":false,"url":null},{"n":"Rihards Berkolds","h":192,"p":"SG","y":2004,"nat":null,"c":"VEF RIGA","co":"Latvia","coD":"Latvia","s":"free","to":null,"tl":null,"isComp":false,"url":null},{"n":"Tomass Latisevs","h":179,"p":"PG","y":2009,"nat":null,"c":"VEF RIGA","co":"Latvia","coD":"Latvia","s":"free","to":null,"tl":null,"isComp":false,"url":null},{"n":"Illya Sydorov","h":186,"p":"PG","y":1996,"nat":"Ukrajina","c":"VEF RIGA","co":"Latvia","coD":"Latvia","s":"free","to":null,"tl":null,"isComp":false,"url":"https://basketball.eurobasket.com/player/Illya-Sydorov/243487"},{"n":"Dairis Bertans","h":193,"p":"G","y":1989,"nat":null,"c":"VEF RIGA","co":"Latvia","coD":"Latvia","s":"free","to":null,"tl":null,"isComp":false,"url":null},{"n":"Rodrigo Bumeisters","h":196,"p":"SG","y":2000,"nat":null,"c":"VEF RIGA","co":"Latvia","coD":"Latvia","s":"free","to":null,"tl":null,"isComp":false,"url":null},{"n":"Maris Gulbis","h":200,"p":"SF","y":1985,"nat":null,"c":"VEF RIGA","co":"Latvia","coD":"Latvia","s":"free","to":null,"tl":null,"isComp":false,"url":null}]}