{"co":"Slovakia","coD":"Slovakia","players":[{"n":"Mate Balogh","h":204,"p":"PF","y":2001,"nat":"Slovaška","c":"BC KOMARNO","co":"Slovakia","coD":"Slovakia","s":null,"to":null,"tl":null,"isComp":false,"url":"https://basketball.eurobasket.com/player/Mate-Balogh/401904"},{"n":"Owen Lobsinger","h":206,"p":"F","y":2002,"nat":"ZDA","c":"BC KOMARNO","co":"Slovakia","coD":"Slovakia","s":"left","to":"Nunawading S.","tl":"NBL One","isComp":false,"url":"https://basketball.australiabasket.com/player/Owen-Lobsinger/615136"},{"n":"Corey McKeithan","h":181,"p":"PG","y":2001,"nat":"Puerto Rican","c":"BC KOMARNO","co":"Slovakia","coD":"Slovakia","s":"left","to":"Santurce","tl":"BSN","isComp":false,"url":"https://basketball.latinbasket.com/player/Corey-McKeithan/526839"},{"n":"Noah Farrakhan","h":185,"p":"G","y":2000,"nat":"ZDA","c":"BC KOMARNO","co":"Slovakia","coD":"Slovakia","s":"free","to":null,"tl":null,"isComp":false,"url":"https://basketball.eurobasket.com/player/Noah-Farrakhan/423598"},{"n":"Tyler Stevenson","h":206,"p":"PF","y":2002,"nat":"ZDA","c":"BC KOMARNO","co":"Slovakia","coD":"Slovakia","s":"free","to":null,"tl":null,"isComp":false,"url":"https://basketball.eurobasket.com/player/Tyler-Stevenson/404715"},{"n":"Tyler Millin","h":201,"p":"F","y":2000,"nat":"ZDA","c":"BC KOMARNO","co":"Slovakia","coD":"Slovakia","s":"free","to":null,"tl":null,"isComp":false,"url":"https://basketball.eurobasket.com/player/Tyler-Millin/498375"},{"n":"Martin Pospisil","h":195,"p":"SF","y":2006,"nat":null,"c":"BC KOMARNO","co":"Slovakia","coD":"Slovakia","s":"free","to":null,"tl":null,"isComp":false,"url":null},{"n":"Carrington Wiggins","h":185,"p":"G","y":2000,"nat":"ZDA","c":"BC KOMARNO","co":"Slovakia","coD":"Slovakia","s":"free","to":null,"tl":null,"isComp":false,"url":"https://basketball.eurobasket.com/player/Carrington-Wiggins/504660"},{"n":"Martin Koller","h":186,"p":"PG","y":2004,"nat":null,"c":"BC KOMARNO","co":"Slovakia","coD":"Slovakia","s":"free","to":null,"tl":null,"isComp":false,"url":null},{"n":"Johnathan Massie","h":198,"p":"G","y":2003,"nat":"ZDA","c":"BC PRIEVIDZA","co":"Slovakia","coD":"Slovakia","s":null,"to":null,"tl":null,"isComp":false,"url":"https://basketball.eurobasket.com/player/Johnathan-Massie/598158"},{"n":"Jakub Mokran","h":200,"p":"F/C","y":1999,"nat":"Španija","c":"BC PRIEVIDZA","co":"Slovakia","coD":"Slovakia","s":null,"to":null,"tl":null,"isComp":false,"url":"https://basketball.eurobasket.com/player/Jakub-Mokran/369159"},{"n":"Aamer Muhammad","h":185,"p":"G","y":2001,"nat":"ZDA","c":"BC PRIEVIDZA","co":"Slovakia","coD":"Slovakia","s":null,"to":null,"tl":null,"isComp":false,"url":"https://basketball.eurobasket.com/player/Aamer-Muhammad/527208"},{"n":"Frankie Policelli","h":206,"p":"F","y":2000,"nat":"ZDA","c":"BC PRIEVIDZA","co":"Slovakia","coD":"Slovakia","s":null,"to":null,"tl":null,"isComp":false,"url":"https://basketball.eurobasket.com/player/Frankie-Policelli/474302"},{"n":"David Novak","h":199,"p":"F","y":2003,"nat":"Slovaška","c":"BC PRIEVIDZA","co":"Slovakia","coD":"Slovakia","s":null,"to":null,"tl":null,"isComp":false,"url":"https://basketball.eurobasket.com/player/David-Novak/524488"},{"n":"Maros Zeliznak","h":211,"p":"C","y":1999,"nat":"Slovaška","c":"BC PRIEVIDZA","co":"Slovakia","coD":"Slovakia","s":null,"to":null,"tl":null,"isComp":false,"url":"https://basketball.eurobasket.com/player/Maros-Zeliznak/369160"},{"n":"Dalibor Hlivak","h":190,"p":"G","y":1995,"nat":"Slovaška","c":"BC PRIEVIDZA","co":"Slovakia","coD":"Slovakia","s":null,"to":null,"tl":null,"isComp":false,"url":"https://basketball.eurobasket.com/player/Dalibor-Hlivak/228033"},{"n":"Eduardo Andre","h":208,"p":"C","y":2001,"nat":"V. Britanija","c":"BC PRIEVIDZA","co":"Slovakia","coD":"Slovakia","s":"free","to":null,"tl":null,"isComp":false,"url":"https://basketball.eurobasket.com/player/Eduardo-Andre/526625"},{"n":"James Bishop IV","h":188,"p":"G","y":2000,"nat":"ZDA","c":"BC PRIEVIDZA","co":"Slovakia","coD":"Slovakia","s":"free","to":null,"tl":null,"isComp":false,"url":"https://basketball.eurobasket.com/player/James-Bishop-IV/422843"},{"n":"Juraj Janosik","h":196,"p":"SF","y":2009,"nat":null,"c":"BC PRIEVIDZA","co":"Slovakia","coD":"Slovakia","s":"free","to":null,"tl":null,"isComp":false,"url":null},{"n":"Samuel Kokavec","h":199,"p":"SF","y":2008,"nat":null,"c":"BC PRIEVIDZA","co":"Slovakia","coD":"Slovakia","s":"free","to":null,"tl":null,"isComp":false,"url":null},{"n":"Jakub Krucky","h":193,"p":"G","y":2007,"nat":null,"c":"BC PRIEVIDZA","co":"Slovakia","coD":"Slovakia","s":"free","to":null,"tl":null,"isComp":false,"url":null},{"n":"Jaaden Lewis","h":185,"p":"G","y":1997,"nat":"Slovaška","c":"BC PRIEVIDZA","co":"Slovakia","coD":"Slovakia","s":"free","to":null,"tl":null,"isComp":false,"url":"https://basketball.eurobasket.com/player/Jaaden-Lewis/406620"},{"n":"Bonke Maring","h":208,"p":"C","y":2000,"nat":"ZDA","c":"BC PRIEVIDZA","co":"Slovakia","coD":"Slovakia","s":"free","to":null,"tl":null,"isComp":false,"url":"https://basketball.eurobasket.com/player/Bonke-Maring/544988"},{"n":"Noah Reynolds","h":190,"p":"G","y":2002,"nat":"ZDA","c":"BC PRIEVIDZA","co":"Slovakia","coD":"Slovakia","s":"free","to":null,"tl":null,"isComp":false,"url":"https://basketball.eurobasket.com/player/Noah-Reynolds/563580"},{"n":"Naje Smith","h":203,"p":"F","y":2000,"nat":"ZDA","c":"BC PRIEVIDZA","co":"Slovakia","coD":"Slovakia","s":"free","to":null,"tl":null,"isComp":false,"url":"https://basketball.eurobasket.com/player/Naje-Smith/502465"},{"n":"Davontrey Thomas","h":196,"p":"F","y":2001,"nat":"ZDA","c":"BC PRIEVIDZA","co":"Slovakia","coD":"Slovakia","s":"free","to":null,"tl":null,"isComp":false,"url":"https://basketball.eurobasket.com/player/Davontrey-Thomas/532899"},{"n":"Sage Tolbert III","h":201,"p":"F","y":1999,"nat":"ZDA","c":"BC PRIEVIDZA","co":"Slovakia","coD":"Slovakia","s":"free","to":null,"tl":null,"isComp":false,"url":"https://basketball.eurobasket.com/player/Sage-Tolbert-III/475524"},{"n":"Joe Toussaint","h":183,"p":"PG","y":2000,"nat":"ZDA","c":"BC PRIEVIDZA","co":"Slovakia","coD":"Slovakia","s":"free","to":null,"tl":null,"isComp":false,"url":"https://basketball.eurobasket.com/player/Joe-Toussaint/439208"},{"n":"Patrik Hrico","h":185,"p":"G","y":2006,"nat":null,"c":"BC PRIEVIDZA","co":"Slovakia","coD":"Slovakia","s":"free","to":null,"tl":null,"isComp":false,"url":null},{"n":"Marek Jass","h":194,"p":"G","y":1990,"nat":null,"c":"BC PRIEVIDZA","co":"Slovakia","coD":"Slovakia","s":"free","to":null,"tl":null,"isComp":false,"url":null},{"n":"David Abrham","h":193,"p":"SF","y":1996,"nat":"Slovaška","c":"BC SLOVAN BRATISLAVA","co":"Slovakia","coD":"Slovakia","s":null,"to":null,"tl":null,"isComp":false,"url":"https://basketball.eurobasket.com/player/David-Abrham/257415"},{"n":"Tomas Pavelka","h":217,"p":"C","y":2000,"nat":"Slovaška","c":"BC SLOVAN BRATISLAVA","co":"Slovakia","coD":"Slovakia","s":null,"to":null,"tl":null,"isComp":false,"url":"https://basketball.eurobasket.com/player/Tomas-Pavelka/445077"},{"n":"Matej Majercak","h":188,"p":"SG","y":1999,"nat":"Slovaška","c":"BC SLOVAN BRATISLAVA","co":"Slovakia","coD":"Slovakia","s":null,"to":null,"tl":null,"isComp":false,"url":"https://basketball.eurobasket.com/player/Matej-Majercak/369155"},{"n":"Milan Szabo","h":190,"p":"SG","y":1998,"nat":"Slovaška","c":"BC SLOVAN BRATISLAVA","co":"Slovakia","coD":"Slovakia","s":null,"to":null,"tl":null,"isComp":false,"url":"https://basketball.eurobasket.com/player/Milan-Szabo/367444"},{"n":"Lester Medford Jr.","h":184,"p":"PG","y":1993,"nat":"ZDA","c":"BC SLOVAN BRATISLAVA","co":"Slovakia","coD":"Slovakia","s":"left","to":"Gambusinos","tl":"LNBP","isComp":false,"url":"https://basketball.latinbasket.com/player/Lester-Medford-Jr/250462"},{"n":"Marko Radovanovic","h":209,"p":"C/F","y":1996,"nat":"Srbija","c":"BC SLOVAN BRATISLAVA","co":"Slovakia","coD":"Slovakia","s":"left","to":"FMP BG","tl":"KLS","isComp":false,"url":"https://basketball.eurobasket.com/player/Marko-Radovanovic/252387"},{"n":"Maros Golian","h":206,"p":"F/C","y":2007,"nat":null,"c":"BC SLOVAN BRATISLAVA","co":"Slovakia","coD":"Slovakia","s":"free","to":null,"tl":null,"isComp":false,"url":null},{"n":"Robert Howard","h":203,"p":"F","y":1997,"nat":"ZDA","c":"BC SLOVAN BRATISLAVA","co":"Slovakia","coD":"Slovakia","s":"free","to":null,"tl":null,"isComp":false,"url":"https://basketball.eurobasket.com/player/Robert-Howard/416161"},{"n":"Christian James","h":194,"p":"PG","y":1996,"nat":"ZDA","c":"BC SLOVAN BRATISLAVA","co":"Slovakia","coD":"Slovakia","s":"free","to":null,"tl":null,"isComp":false,"url":"https://basketball.eurobasket.com/player/Christian-James/370782"},{"n":"Stefan Pot","h":195,"p":"G","y":1994,"nat":"Srbija","c":"BC SLOVAN BRATISLAVA","co":"Slovakia","coD":"Slovakia","s":"free","to":null,"tl":null,"isComp":false,"url":"https://basketball.eurobasket.com/player/Stefan-Pot/192471"},{"n":"Bruno Randuska","h":191,"p":"PG","y":2008,"nat":null,"c":"BC SLOVAN BRATISLAVA","co":"Slovakia","coD":"Slovakia","s":"free","to":null,"tl":null,"isComp":false,"url":null},{"n":"Shamiel Stevenson","h":198,"p":"SG","y":1998,"nat":"Kanada","c":"BC SLOVAN BRATISLAVA","co":"Slovakia","coD":"Slovakia","s":"free","to":null,"tl":null,"isComp":false,"url":"https://basketball.eurobasket.com/player/Shamiel-Stevenson/400078"},{"n":"Raynere Thornton","h":201,"p":"F","y":1997,"nat":"ZDA","c":"BC SLOVAN BRATISLAVA","co":"Slovakia","coD":"Slovakia","s":"free","to":null,"tl":null,"isComp":false,"url":"https://basketball.eurobasket.com/player/Raynere-Thornton/429575"},{"n":"Jordan Watson","h":188,"p":"PG","y":1995,"nat":"ZDA","c":"BC SLOVAN BRATISLAVA","co":"Slovakia","coD":"Slovakia","s":"free","to":null,"tl":null,"isComp":false,"url":"https://basketball.eurobasket.com/player/Jordan-Watson/347631"},{"n":"Ivan Zidzik","h":208,"p":"C","y":1990,"nat":null,"c":"BC SLOVAN BRATISLAVA","co":"Slovakia","coD":"Slovakia","s":"free","to":null,"tl":null,"isComp":false,"url":null},{"n":"Robert Hudec","h":191,"p":"SG","y":2005,"nat":null,"c":"BC SLOVAN BRATISLAVA","co":"Slovakia","coD":"Slovakia","s":"free","to":null,"tl":null,"isComp":false,"url":null},{"n":"David Harabin","h":207,"p":"F/C","y":2002,"nat":"Slovaška","c":"BK ISKRA SVIT","co":"Slovakia","coD":"Slovakia","s":null,"to":null,"tl":null,"isComp":false,"url":"https://basketball.eurobasket.com/player/David-Harabin/573944"},{"n":"Daniel Blasko","h":183,"p":"G","y":2005,"nat":"Slovaška","c":"BK ISKRA SVIT","co":"Slovakia","coD":"Slovakia","s":null,"to":null,"tl":null,"isComp":false,"url":"https://basketball.eurobasket.com/player/Daniel-Blasko/668384"},{"n":"Sevon Witt","h":203,"p":"F","y":1999,"nat":"ZDA","c":"BK ISKRA SVIT","co":"Slovakia","coD":"Slovakia","s":"left","to":"Liege","tl":"Pro Basketball League","isComp":false,"url":"https://basketball.eurobasket.com/player/Sevon-Witt/488348"},{"n":"Donavan Yap","h":196,"p":"G","y":2002,"nat":"ZDA","c":"BK ISKRA SVIT","co":"Slovakia","coD":"Slovakia","s":"free","to":null,"tl":null,"isComp":false,"url":"https://basketball.eurobasket.com/player/Donavan-Yap/560951"},{"n":"TJ Atwood","h":198,"p":"G","y":1997,"nat":"ZDA","c":"BK ISKRA SVIT","co":"Slovakia","coD":"Slovakia","s":"free","to":null,"tl":null,"isComp":false,"url":"https://basketball.eurobasket.com/player/TJ-Atwood/402631"},{"n":"Maishe Dailey","h":200,"p":"G","y":1998,"nat":"ZDA","c":"BK ISKRA SVIT","co":"Slovakia","coD":"Slovakia","s":"free","to":null,"tl":null,"isComp":false,"url":"https://basketball.eurobasket.com/player/Maishe-Dailey/402174"},{"n":"Lukas Jendrichovsky","h":189,"p":"PG","y":2006,"nat":null,"c":"BK ISKRA SVIT","co":"Slovakia","coD":"Slovakia","s":"free","to":null,"tl":null,"isComp":false,"url":null},{"n":"Avery Sullivan","h":203,"p":"F/C","y":1999,"nat":"ZDA","c":"BK ISKRA SVIT","co":"Slovakia","coD":"Slovakia","s":"free","to":null,"tl":null,"isComp":false,"url":"https://basketball.eurobasket.com/player/Avery-Sullivan/430994"},{"n":"Robert Rozanek","h":191,"p":"G","y":1996,"nat":null,"c":"BK ISKRA SVIT","co":"Slovakia","coD":"Slovakia","s":"free","to":null,"tl":null,"isComp":false,"url":null},{"n":"Julius Matusek","h":200,"p":"F","y":2005,"nat":null,"c":"BK ISKRA SVIT","co":"Slovakia","coD":"Slovakia","s":"free","to":null,"tl":null,"isComp":false,"url":null},{"n":"Simon Turza","h":192,"p":"G","y":2000,"nat":null,"c":"BK ISKRA SVIT","co":"Slovakia","coD":"Slovakia","s":"free","to":null,"tl":null,"isComp":false,"url":null},{"n":"Juraj Lastic","h":188,"p":"G","y":2001,"nat":"Slovaška","c":"BKM LUCENEC","co":"Slovakia","coD":"Slovakia","s":null,"to":null,"tl":null,"isComp":false,"url":"https://basketball.eurobasket.com/player/Juraj-Lastic/529152"},{"n":"Lukas Kulcar","h":182,"p":"G","y":2005,"nat":"Slovaška","c":"BKM LUCENEC","co":"Slovakia","coD":"Slovakia","s":null,"to":null,"tl":null,"isComp":false,"url":"https://basketball.eurobasket.com/player/Lukas-Kulcar/640898"},{"n":"Matej Siladi","h":195,"p":"SF","y":2000,"nat":"Slovaška","c":"BKM LUCENEC","co":"Slovakia","coD":"Slovakia","s":null,"to":null,"tl":null,"isComp":false,"url":"https://basketball.eurobasket.com/player/Matej-Siladi/477225"},{"n":"Eric Boone","h":188,"p":"F","y":1999,"nat":"ZDA","c":"BKM LUCENEC","co":"Slovakia","coD":"Slovakia","s":"left","to":"Brussels","tl":"Pro Basketball League","isComp":false,"url":"https://basketball.eurobasket.com/player/Eric-Boone/498890"},{"n":"Shaun Willett","h":193,"p":"G/F","y":1996,"nat":"ZDA","c":"BKM LUCENEC","co":"Slovakia","coD":"Slovakia","s":"left","to":"Panteras","tl":"LNBP","isComp":false,"url":"https://basketball.latinbasket.com/player/Shaun-Willett/429620"},{"n":"Jalil Beaubrun","h":206,"p":"F","y":2002,"nat":"ZDA","c":"BKM LUCENEC","co":"Slovakia","coD":"Slovakia","s":"free","to":null,"tl":null,"isComp":false,"url":"https://basketball.eurobasket.com/player/Jalil-Beaubrun/500261"},{"n":"Tervell Beck","h":201,"p":"C","y":1996,"nat":"ZDA","c":"BKM LUCENEC","co":"Slovakia","coD":"Slovakia","s":"free","to":null,"tl":null,"isComp":false,"url":"https://basketball.eurobasket.com/player/Tervell-Beck/337655"},{"n":"Jakub Meress","h":200,"p":"PF","y":1996,"nat":null,"c":"BKM LUCENEC","co":"Slovakia","coD":"Slovakia","s":"free","to":null,"tl":null,"isComp":false,"url":null},{"n":"Lukas Hutka","h":197,"p":"SG","y":2008,"nat":null,"c":"BKM LUCENEC","co":"Slovakia","coD":"Slovakia","s":"free","to":null,"tl":null,"isComp":false,"url":null},{"n":"Matus Zlocha","h":190,"p":"G","y":2008,"nat":null,"c":"BKM LUCENEC","co":"Slovakia","coD":"Slovakia","s":"free","to":null,"tl":null,"isComp":false,"url":null},{"n":"Matus Skuben","h":190,"p":"F","y":2001,"nat":null,"c":"BKM LUCENEC","co":"Slovakia","coD":"Slovakia","s":"free","to":null,"tl":null,"isComp":false,"url":null},{"n":"Karlis Azacis","h":200,"p":"F","y":2007,"nat":null,"c":"INTER SB BRATISLAVA","co":"Slovakia","coD":"Slovakia","s":"free","to":null,"tl":null,"isComp":false,"url":null},{"n":"Benjamin Boros","h":184,"p":"G","y":2008,"nat":null,"c":"INTER SB BRATISLAVA","co":"Slovakia","coD":"Slovakia","s":"free","to":null,"tl":null,"isComp":false,"url":null},{"n":"Mojmir Deen","h":200,"p":"C","y":2007,"nat":null,"c":"INTER SB BRATISLAVA","co":"Slovakia","coD":"Slovakia","s":"free","to":null,"tl":null,"isComp":false,"url":null},{"n":"Michal Demko","h":198,"p":"F","y":2005,"nat":null,"c":"INTER SB BRATISLAVA","co":"Slovakia","coD":"Slovakia","s":"free","to":null,"tl":null,"isComp":false,"url":null},{"n":"Matus Gregor","h":192,"p":"G","y":2008,"nat":null,"c":"INTER SB BRATISLAVA","co":"Slovakia","coD":"Slovakia","s":"free","to":null,"tl":null,"isComp":false,"url":null},{"n":"Tobias Gregor","h":190,"p":"PG","y":2007,"nat":null,"c":"INTER SB BRATISLAVA","co":"Slovakia","coD":"Slovakia","s":"free","to":null,"tl":null,"isComp":false,"url":null},{"n":"Martin Lukjanec","h":197,"p":"F","y":2009,"nat":null,"c":"INTER SB BRATISLAVA","co":"Slovakia","coD":"Slovakia","s":"free","to":null,"tl":null,"isComp":false,"url":null},{"n":"Martin Minarovjech","h":201,"p":"F/G","y":2007,"nat":null,"c":"INTER SB BRATISLAVA","co":"Slovakia","coD":"Slovakia","s":"free","to":null,"tl":null,"isComp":false,"url":null},{"n":"Adam Pukancik","h":196,"p":"F","y":2008,"nat":null,"c":"INTER SB BRATISLAVA","co":"Slovakia","coD":"Slovakia","s":"free","to":null,"tl":null,"isComp":false,"url":null},{"n":"Alex Valocsay","h":193,"p":"G","y":2008,"nat":null,"c":"INTER SB BRATISLAVA","co":"Slovakia","coD":"Slovakia","s":"free","to":null,"tl":null,"isComp":false,"url":null},{"n":"Zek Montgomery","h":198,"p":"G","y":2002,"nat":"ZDA","c":"KOSICE WOLVES","co":"Slovakia","coD":"Slovakia","s":"free","to":null,"tl":null,"isComp":false,"url":"https://basketball.eurobasket.com/player/Zek-Montgomery/557699"},{"n":"Marko Perovic","h":204,"p":"C","y":1992,"nat":"Črna gora","c":"KOSICE WOLVES","co":"Slovakia","coD":"Slovakia","s":"free","to":null,"tl":null,"isComp":false,"url":"https://basketball.eurobasket.com/player/Marko-Perovic/87075"},{"n":"Dmytro Sokolovskyi","h":190,"p":"PG","y":2004,"nat":null,"c":"KOSICE WOLVES","co":"Slovakia","coD":"Slovakia","s":"free","to":null,"tl":null,"isComp":false,"url":null},{"n":"Jalen Gaffney","h":191,"p":"G","y":2000,"nat":"ZDA","c":"KOSICE WOLVES","co":"Slovakia","coD":"Slovakia","s":"free","to":null,"tl":null,"isComp":false,"url":"https://basketball.eurobasket.com/player/Jalen-Gaffney/407438"},{"n":"Filip Halada","h":194,"p":"F","y":1992,"nat":"Czech Republic","c":"KOSICE WOLVES","co":"Slovakia","coD":"Slovakia","s":"free","to":null,"tl":null,"isComp":false,"url":"https://basketball.eurobasket.com/player/Filip-Halada/184597"},{"n":"Myles Howard","h":206,"p":"C","y":1998,"nat":"ZDA","c":"KOSICE WOLVES","co":"Slovakia","coD":"Slovakia","s":"free","to":null,"tl":null,"isComp":false,"url":"https://basketball.eurobasket.com/player/Myles-Howard/404785"},{"n":"AJ John","h":202,"p":"F","y":1996,"nat":"Grenadian","c":"KOSICE WOLVES","co":"Slovakia","coD":"Slovakia","s":"free","to":null,"tl":null,"isComp":false,"url":"https://basketball.eurobasket.com/player/AJ-John/336007"},{"n":"Matus Makula","h":180,"p":"PG","y":2005,"nat":null,"c":"KOSICE WOLVES","co":"Slovakia","coD":"Slovakia","s":"free","to":null,"tl":null,"isComp":false,"url":null},{"n":"Adam Moncek","h":190,"p":"G","y":2000,"nat":null,"c":"KOSICE WOLVES","co":"Slovakia","coD":"Slovakia","s":"free","to":null,"tl":null,"isComp":false,"url":null},{"n":"Julian Vaughns","h":190,"p":"PG","y":2001,"nat":"ZDA","c":"KOSICE WOLVES","co":"Slovakia","coD":"Slovakia","s":"free","to":null,"tl":null,"isComp":false,"url":"https://basketball.eurobasket.com/player/Julian-Vaughns/533621"},{"n":"Robert Seman","h":185,"p":"G","y":2004,"nat":null,"c":"KOSICE WOLVES","co":"Slovakia","coD":"Slovakia","s":"free","to":null,"tl":null,"isComp":false,"url":null},{"n":"Michal Dolnik","h":203,"p":"C","y":1995,"nat":"Slovaška","c":"MBK BANIK HANDLOVA","co":"Slovakia","coD":"Slovakia","s":null,"to":null,"tl":null,"isComp":false,"url":"https://basketball.eurobasket.com/player/Michal-Dolnik/259327"},{"n":"Samuel Horvath","h":187,"p":"PG","y":2001,"nat":"Slovaška","c":"MBK BANIK HANDLOVA","co":"Slovakia","coD":"Slovakia","s":null,"to":null,"tl":null,"isComp":false,"url":"https://basketball.eurobasket.com/player/Samuel-Horvath/396607"},{"n":"Viliam Durecko","h":194,"p":"SF","y":2005,"nat":"Slovaška","c":"MBK BANIK HANDLOVA","co":"Slovakia","coD":"Slovakia","s":null,"to":null,"tl":null,"isComp":false,"url":"https://basketball.eurobasket.com/player/Viliam-Durecko/640934"},{"n":"Jakub Petras","h":209,"p":"F","y":1994,"nat":"Slovaška","c":"MBK BANIK HANDLOVA","co":"Slovakia","coD":"Slovakia","s":null,"to":null,"tl":null,"isComp":false,"url":"https://basketball.eurobasket.com/player/Jakub-Petras/203677"},{"n":"Olexandr Belikov","h":202,"p":"G/F","y":1992,"nat":"Ukrajina","c":"MBK BANIK HANDLOVA","co":"Slovakia","coD":"Slovakia","s":"left","to":"Decin","tl":"NBL","isComp":false,"url":"https://basketball.eurobasket.com/player/Olexandr-Belikov/181290"},{"n":"C.J. Jackson","h":185,"p":"PG","y":1996,"nat":"ZDA","c":"MBK BANIK HANDLOVA","co":"Slovakia","coD":"Slovakia","s":"left","to":"Dolphins","tl":"VBA","isComp":false,"url":"https://basketball.asia-basket.com/player/CJ-Jackson/389677"},{"n":"Curtis Jones","h":191,"p":"G","y":1997,"nat":"ZDA","c":"MBK BANIK HANDLOVA","co":"Slovakia","coD":"Slovakia","s":"left","to":"Muenster","tl":"ProA","isComp":false,"url":"https://basketball.eurobasket.com/player/Curtis-Jones/402171"},{"n":"Juraj Lastic","h":188,"p":"G","y":2001,"nat":"Slovaška","c":"MBK BANIK HANDLOVA","co":"Slovakia","coD":"Slovakia","s":"left","to":"Lucenec","tl":"Tipos SBL","isComp":false,"url":"https://basketball.eurobasket.com/player/Juraj-Lastic/529152"},{"n":"Jeremy McLaughlin","h":203,"p":"PF","y":1995,"nat":"ZDA","c":"MBK BANIK HANDLOVA","co":"Slovakia","coD":"Slovakia","s":"left","to":"Hawks","tl":"NBL","isComp":false,"url":"https://basketball.australiabasket.com/player/Jeremy-McLaughlin/346130"},{"n":"Petar Dragovic","h":null,"p":null,"y":2000,"nat":"Črna gora","c":"MBK BANIK HANDLOVA","co":"Slovakia","coD":"Slovakia","s":"free","to":null,"tl":null,"isComp":false,"url":"https://basketball.eurobasket.com/player/Petar-Dragovic/314908"},{"n":"Marek Foltin","h":184,"p":"PG","y":2002,"nat":null,"c":"MBK BANIK HANDLOVA","co":"Slovakia","coD":"Slovakia","s":"free","to":null,"tl":null,"isComp":false,"url":null},{"n":"Jordan Harris","h":185,"p":"G","y":1999,"nat":"ZDA","c":"MBK BANIK HANDLOVA","co":"Slovakia","coD":"Slovakia","s":"free","to":null,"tl":null,"isComp":false,"url":"https://basketball.eurobasket.com/player/Jordan-Harris/466475"},{"n":"Djimon Henson","h":193,"p":"G","y":1998,"nat":"ZDA","c":"MBK BANIK HANDLOVA","co":"Slovakia","coD":"Slovakia","s":"free","to":null,"tl":null,"isComp":false,"url":"https://basketball.eurobasket.com/player/Djimon-Henson/403039"},{"n":"Peter Kovacik","h":190,"p":"G","y":2005,"nat":null,"c":"MBK BANIK HANDLOVA","co":"Slovakia","coD":"Slovakia","s":"free","to":null,"tl":null,"isComp":false,"url":null},{"n":"Marko Vransky","h":188,"p":"PG","y":2002,"nat":null,"c":"MBK BANIK HANDLOVA","co":"Slovakia","coD":"Slovakia","s":"free","to":null,"tl":null,"isComp":false,"url":null},{"n":"Lukas Bolek","h":194,"p":"SG","y":1997,"nat":"Slovaška","c":"NITRA BLUE WINGS","co":"Slovakia","coD":"Slovakia","s":null,"to":null,"tl":null,"isComp":false,"url":"https://basketball.eurobasket.com/player/Lukas-Bolek/335886"},{"n":"Dimitrius Underwood","h":193,"p":"F","y":1998,"nat":"ZDA","c":"NITRA BLUE WINGS","co":"Slovakia","coD":"Slovakia","s":"left","to":"Pitesti","tl":"Liga Nationala","isComp":false,"url":"https://basketball.eurobasket.com/player/Dimitrius-Underwood/417333"},{"n":"Jeremiah Bailey","h":201,"p":"F","y":1998,"nat":"ZDA","c":"NITRA BLUE WINGS","co":"Slovakia","coD":"Slovakia","s":"free","to":null,"tl":null,"isComp":false,"url":"https://basketball.eurobasket.com/player/Jeremiah-Bailey/463770"},{"n":"Brandon Horvath","h":208,"p":"F/C","y":1999,"nat":"ZDA","c":"NITRA BLUE WINGS","co":"Slovakia","coD":"Slovakia","s":"free","to":null,"tl":null,"isComp":false,"url":"https://basketball.eurobasket.com/player/Brandon-Horvath/451188"},{"n":"Simon Hoferica","h":189,"p":"SG","y":2006,"nat":null,"c":"NITRA BLUE WINGS","co":"Slovakia","coD":"Slovakia","s":"free","to":null,"tl":null,"isComp":false,"url":null},{"n":"Tristan Ikpe","h":198,"p":"F","y":1999,"nat":"ZDA","c":"NITRA BLUE WINGS","co":"Slovakia","coD":"Slovakia","s":"free","to":null,"tl":null,"isComp":false,"url":"https://basketball.eurobasket.com/player/Tristan-Ikpe/501885"},{"n":"Guy Ragland Jr.","h":203,"p":"F","y":2002,"nat":"U.S. Virgin Islands","c":"NITRA BLUE WINGS","co":"Slovakia","coD":"Slovakia","s":"free","to":null,"tl":null,"isComp":false,"url":"https://basketball.eurobasket.com/player/Guy-Ragland-Jr/568207"},{"n":"Maros Simko","h":199,"p":"F","y":2005,"nat":null,"c":"NITRA BLUE WINGS","co":"Slovakia","coD":"Slovakia","s":"free","to":null,"tl":null,"isComp":false,"url":null},{"n":"Radoslav Telicak","h":199,"p":"C","y":2005,"nat":null,"c":"NITRA BLUE WINGS","co":"Slovakia","coD":"Slovakia","s":"free","to":null,"tl":null,"isComp":false,"url":null},{"n":"Lubomir Urban","h":193,"p":"SG","y":2005,"nat":null,"c":"NITRA BLUE WINGS","co":"Slovakia","coD":"Slovakia","s":"free","to":null,"tl":null,"isComp":false,"url":null},{"n":"Martin Chlupis","h":195,"p":"F","y":2006,"nat":"Czech Republic","c":"NITRA BLUE WINGS","co":"Slovakia","coD":"Slovakia","s":"free","to":null,"tl":null,"isComp":false,"url":"https://basketball.eurobasket.com/player/Martin-Chlupis/617859"},{"n":"Michal Fusek","h":223,"p":"C","y":1995,"nat":"Slovaška","c":"NITRA BLUE WINGS","co":"Slovakia","coD":"Slovakia","s":"free","to":null,"tl":null,"isComp":false,"url":"https://basketball.eurobasket.com/player/Michal-Fusek/261330"},{"n":"Adam Galko","h":205,"p":"F","y":2004,"nat":null,"c":"NITRA BLUE WINGS","co":"Slovakia","coD":"Slovakia","s":"free","to":null,"tl":null,"isComp":false,"url":null},{"n":"Andrej Nahlik","h":192,"p":"G","y":2006,"nat":null,"c":"NITRA BLUE WINGS","co":"Slovakia","coD":"Slovakia","s":"free","to":null,"tl":null,"isComp":false,"url":null},{"n":"Tahlik Chavez","h":188,"p":"G","y":2001,"nat":"ZDA","c":"PATRIOTI LEVICE","co":"Slovakia","coD":"Slovakia","s":null,"to":null,"tl":null,"isComp":false,"url":"https://basketball.eurobasket.com/player/Tahlik-Chavez/428764"},{"n":"Filip Horvath","h":188,"p":"PG","y":2007,"nat":"Czech Republic","c":"PATRIOTI LEVICE","co":"Slovakia","coD":"Slovakia","s":null,"to":null,"tl":null,"isComp":false,"url":"https://basketball.eurobasket.com/player/Filip-Horvath/640410"},{"n":"Samuel Volarik","h":194,"p":"F/G","y":2000,"nat":"Slovaška","c":"PATRIOTI LEVICE","co":"Slovakia","coD":"Slovakia","s":null,"to":null,"tl":null,"isComp":false,"url":"https://basketball.eurobasket.com/player/Samuel-Volarik/478419"},{"n":"Ladislav Gergely","h":204,"p":"C","y":2005,"nat":"Slovaška","c":"PATRIOTI LEVICE","co":"Slovakia","coD":"Slovakia","s":null,"to":null,"tl":null,"isComp":false,"url":"https://basketball.eurobasket.com/player/Ladislav-Gergely/640309"},{"n":"Patrik Pazicky","h":193,"p":"G/F","y":2002,"nat":"Slovaška","c":"PATRIOTI LEVICE","co":"Slovakia","coD":"Slovakia","s":null,"to":null,"tl":null,"isComp":false,"url":"https://basketball.eurobasket.com/player/Patrik-Pazicky/479179"},{"n":"Boris Bojanovsky","h":217,"p":"C","y":1993,"nat":"Slovaška","c":"PATRIOTI LEVICE","co":"Slovakia","coD":"Slovakia","s":null,"to":null,"tl":null,"isComp":false,"url":"https://basketball.eurobasket.com/player/Boris-Bojanovsky/182606"},{"n":"Aleksandar Bursac","h":205,"p":"PF","y":1995,"nat":"Hrvaška","c":"PATRIOTI LEVICE","co":"Slovakia","coD":"Slovakia","s":"free","to":null,"tl":null,"isComp":false,"url":"https://basketball.eurobasket.com/player/Aleksandar-Bursac/258589"},{"n":"Omotayo Ogundiran","h":180,"p":"PG","y":1996,"nat":"Nigerija","c":"PATRIOTI LEVICE","co":"Slovakia","coD":"Slovakia","s":"free","to":null,"tl":null,"isComp":false,"url":"https://basketball.eurobasket.com/player/Omotayo-Ogundiran/377014"},{"n":"Tanner Stuckman","h":206,"p":"F","y":1997,"nat":"ZDA","c":"PATRIOTI LEVICE","co":"Slovakia","coD":"Slovakia","s":"free","to":null,"tl":null,"isComp":false,"url":"https://basketball.eurobasket.com/player/Tanner-Stuckman/404927"},{"n":"Daniel Chaban","h":184,"p":"PG","y":2002,"nat":null,"c":"PATRIOTI LEVICE","co":"Slovakia","coD":"Slovakia","s":"free","to":null,"tl":null,"isComp":false,"url":null},{"n":"Rickey McGill","h":188,"p":"G","y":1997,"nat":"ZDA","c":"PATRIOTI LEVICE","co":"Slovakia","coD":"Slovakia","s":"free","to":null,"tl":null,"isComp":false,"url":"https://basketball.eurobasket.com/player/Rickey-McGill/381069"},{"n":"Andre Wesson","h":198,"p":"F","y":1997,"nat":"ZDA","c":"PATRIOTI LEVICE","co":"Slovakia","coD":"Slovakia","s":"free","to":null,"tl":null,"isComp":false,"url":"https://basketball.eurobasket.com/player/Andre-Wesson/402189"},{"n":"Aatu Kivimaki","h":185,"p":"PG","y":1997,"nat":"Finska","c":"PATRIOTI LEVICE","co":"Slovakia","coD":"Slovakia","s":"free","to":null,"tl":null,"isComp":false,"url":"https://basketball.eurobasket.com/player/Aatu-Kivimaki/261908"},{"n":"Alex Krajcovic","h":197,"p":"F","y":2004,"nat":null,"c":"PATRIOTI LEVICE","co":"Slovakia","coD":"Slovakia","s":"free","to":null,"tl":null,"isComp":false,"url":null},{"n":"Samuel Kincel","h":206,"p":"C","y":2000,"nat":"Slovaška","c":"SPISSKI RYTIERI NOVA VES","co":"Slovakia","coD":"Slovakia","s":null,"to":null,"tl":null,"isComp":false,"url":"https://basketball.eurobasket.com/player/Samuel-Kincel/478421"},{"n":"Tomas Mrvis","h":200,"p":"SF","y":1991,"nat":"Slovaška","c":"SPISSKI RYTIERI NOVA VES","co":"Slovakia","coD":"Slovakia","s":null,"to":null,"tl":null,"isComp":false,"url":"https://basketball.eurobasket.com/player/Tomas-Mrvis/131304"},{"n":"Josh Jefferson","h":188,"p":"G","y":1998,"nat":"ZDA","c":"SPISSKI RYTIERI NOVA VES","co":"Slovakia","coD":"Slovakia","s":"left","to":"Nevezis","tl":"LKL","isComp":false,"url":"https://basketball.eurobasket.com/player/Josh-Jefferson/416193"},{"n":"Andrija Draskovic","h":196,"p":"G","y":1994,"nat":"Srbija","c":"SPISSKI RYTIERI NOVA VES","co":"Slovakia","coD":"Slovakia","s":"free","to":null,"tl":null,"isComp":false,"url":"https://basketball.eurobasket.com/player/Andrija-Draskovic/408986"},{"n":"Cameron Jones","h":198,"p":"G","y":1999,"nat":"ZDA","c":"SPISSKI RYTIERI NOVA VES","co":"Slovakia","coD":"Slovakia","s":"free","to":null,"tl":null,"isComp":false,"url":"https://basketball.eurobasket.com/player/Cameron-Jones/475405"},{"n":"Jason Gallant","h":193,"p":"G","y":2002,"nat":"ZDA","c":"SPISSKI RYTIERI NOVA VES","co":"Slovakia","coD":"Slovakia","s":"free","to":null,"tl":null,"isComp":false,"url":"https://basketball.eurobasket.com/player/Jason-Gallant/556383"},{"n":"Isaiah Hill","h":183,"p":"PG","y":2000,"nat":"ZDA","c":"SPISSKI RYTIERI NOVA VES","co":"Slovakia","coD":"Slovakia","s":"free","to":null,"tl":null,"isComp":false,"url":"https://basketball.eurobasket.com/player/Isaiah-Hill/424161"},{"n":"Andrej Ovciarik","h":202,"p":"PF","y":1998,"nat":null,"c":"SPISSKI RYTIERI NOVA VES","co":"Slovakia","coD":"Slovakia","s":"free","to":null,"tl":null,"isComp":false,"url":null},{"n":"Marko Stevanovic","h":203,"p":"F","y":1994,"nat":"Srbija","c":"SPISSKI RYTIERI NOVA VES","co":"Slovakia","coD":"Slovakia","s":"free","to":null,"tl":null,"isComp":false,"url":"https://basketball.eurobasket.com/player/Marko-Stevanovic/263997"},{"n":"Jan Balogac","h":194,"p":"SF","y":2004,"nat":null,"c":"SPISSKI RYTIERI NOVA VES","co":"Slovakia","coD":"Slovakia","s":"free","to":null,"tl":null,"isComp":false,"url":null},{"n":"Juraj Palenik","h":200,"p":"SF","y":2000,"nat":null,"c":"SPISSKI RYTIERI NOVA VES","co":"Slovakia","coD":"Slovakia","s":"free","to":null,"tl":null,"isComp":false,"url":null},{"n":"Martin Pivovar","h":183,"p":"PG","y":2009,"nat":null,"c":"SPISSKI RYTIERI NOVA VES","co":"Slovakia","coD":"Slovakia","s":"free","to":null,"tl":null,"isComp":false,"url":null},{"n":"Matej Zuscak","h":195,"p":"SF","y":2004,"nat":null,"c":"SPISSKI RYTIERI NOVA VES","co":"Slovakia","coD":"Slovakia","s":"free","to":null,"tl":null,"isComp":false,"url":null},{"n":"Adam Antoni","h":193,"p":"SF","y":1995,"nat":null,"c":"SPISSKI RYTIERI NOVA VES","co":"Slovakia","coD":"Slovakia","s":"free","to":null,"tl":null,"isComp":false,"url":null}]}